{"MhceeLrM2_3mcKw5EGLY6A": ["MhceeLrM2_3mcKw5EGLY6A", ["Thai", "Noodles", "Chicken Wings"]], "B3_K2kUVbYOU0VaLcj_LTw": ["B3_K2kUVbYOU0VaLcj_LTw", ["Thai", "Asian Fusion"]], "-OixbLnFLCzQclxCSbUQ8w": ["-OixbLnFLCzQclxCSbUQ8w", ["Thai", "Asian Fusion"]], "VoAuIReq_cPUrFwxbWqG_Q": ["VoAuIReq_cPUrFwxbWqG_Q", ["Thai"]], "KHdYPT0jUnUGdHGaY73mxg": ["KHdYPT0jUnUGdHGaY73mxg", ["Thai"]], "NN3mOWF5e_pnR1ArqM2bHQ": ["NN3mOWF5e_pnR1ArqM2bHQ", ["Vietnamese", "Thai", "Asian Fusion"]], "O1fUmxt3kbV-rnyjBtzAfw": ["O1fUmxt3kbV-rnyjBtzAfw", ["Thai", "Noodles", "Asian Fusion"]], "rKeLuHDI3PQZsPSVCEMHtw": ["rKeLuHDI3PQZsPSVCEMHtw", ["Thai"]], "jjJc_CrkB2HodEinB6cWww": ["jjJc_CrkB2HodEinB6cWww", ["Thai", "Malaysian", "Vietnamese"]], "UC3n_0vZ5zI1fvi7UzNZAg": ["UC3n_0vZ5zI1fvi7UzNZAg", ["Thai", "Vegetarian"]], "-XYp6w50XbZfS90YddS5ew": ["-XYp6w50XbZfS90YddS5ew", ["Thai", "Bars", "Noodles"]], "BF6pY829iPBERt15CG1g3w": ["BF6pY829iPBERt15CG1g3w", ["Thai", "Bars"]], "wGFSTTB6b4MHJJUzBnVJeg": ["wGFSTTB6b4MHJJUzBnVJeg", ["Thai", "Cocktail Bars", "Halal"]], "43r4ynjeIZeQI1w7SWARuQ": ["43r4ynjeIZeQI1w7SWARuQ", ["Thai", "Noodles"]], "5-cv4xv4IBao7N1LSH6tHA": ["5-cv4xv4IBao7N1LSH6tHA", ["Thai"]], "L2ZW-MdvRJ3gM2RIq8STbA": ["L2ZW-MdvRJ3gM2RIq8STbA", ["Thai"]], "83BXSwE0166sObnXLUE4bQ": ["83BXSwE0166sObnXLUE4bQ", ["Thai"]], "qfZFjUnekCQRvZaZJkOPog": ["qfZFjUnekCQRvZaZJkOPog", ["Thai"]], "SZQqAil4kuXhNCLR7_6khg": ["SZQqAil4kuXhNCLR7_6khg", ["Karaoke", "Thai"]], "oWBDdSamOzxMJzsD_-seXg": ["oWBDdSamOzxMJzsD_-seXg", ["Thai"]], "YS8pw7sYOBqaW23FCOqecg": ["YS8pw7sYOBqaW23FCOqecg", ["Thai", "Vegan"]], "vA2VEhW6S1ioX6tXtQdO9A": ["vA2VEhW6S1ioX6tXtQdO9A", ["Thai"]], "f4ZveYR7fuBp_9klL8OgYQ": ["f4ZveYR7fuBp_9klL8OgYQ", ["Thai"]], "_ucIHYqW0ZwAdzaEIYnnsA": ["_ucIHYqW0ZwAdzaEIYnnsA", ["Thai"]], "0IFDnYf3bhqxJR6hVrG7Gw": ["0IFDnYf3bhqxJR6hVrG7Gw", ["Thai", "Halal", "Cocktail Bars"]], "d8lAkqk2w3Lp9uiI4svu6w": ["d8lAkqk2w3Lp9uiI4svu6w", ["Thai", "Noodles"]], "_c0MxccsmIBZcGLJpb4nSA": ["_c0MxccsmIBZcGLJpb4nSA", ["Thai"]], "eGIY_25KFspf8KefDQMj-Q": ["eGIY_25KFspf8KefDQMj-Q", ["Thai"]], "c7z96m0UdMkJRhlz0Ht5XQ": ["c7z96m0UdMkJRhlz0Ht5XQ", ["Thai"]], "z1OgXX3L9Ipl2mu-Hf4ADw": ["z1OgXX3L9Ipl2mu-Hf4ADw", ["Thai", "Bars", "Asian Fusion"]], "coQAQmIKG9dBPA6-RHqJag": ["coQAQmIKG9dBPA6-RHqJag", ["Thai"]], "er4E7VCjDo0xE_IPu5o6Ig": ["er4E7VCjDo0xE_IPu5o6Ig", ["Thai", "Bars"]], "_Ge2eC89Z-jlaDDWglfT8g": ["_Ge2eC89Z-jlaDDWglfT8g", ["Thai", "Chinese", "Salad"]], "CDa0GJZDMPcjvhbx7RbG5Q": ["CDa0GJZDMPcjvhbx7RbG5Q", ["Thai", "Noodles", "Asian Fusion"]], "WM2tNgae2GSiUu-UPdbk6w": ["WM2tNgae2GSiUu-UPdbk6w", ["Thai"]], "liZmIO0FqZwslLJfLDkfgw": ["liZmIO0FqZwslLJfLDkfgw", ["Thai"]], "O8i5XlvcfzH1q-wpfURrpg": ["O8i5XlvcfzH1q-wpfURrpg", ["Thai"]], "-Q8MYIWoE4EsGQtudIOY0w": ["-Q8MYIWoE4EsGQtudIOY0w", ["Thai", "Ramen", "Sushi Bars"]], "p2zm0HnXZkI2yCAuYLb45g": ["p2zm0HnXZkI2yCAuYLb45g", ["Thai", "Noodles", "Soup"]], "y_Ei1zBq6pDW6sMyP8ZSyg": ["y_Ei1zBq6pDW6sMyP8ZSyg", ["Thai"]], "yQiII2hHgV5aEMtIA2VG0Q": ["yQiII2hHgV5aEMtIA2VG0Q", ["Thai"]], "WJS06XxRdc6DD1s4LWE9HA": ["WJS06XxRdc6DD1s4LWE9HA", ["Seafood", "Thai", "Live/Raw Food"]], "JzD9nfJWHwnG-2Wk87muHg": ["JzD9nfJWHwnG-2Wk87muHg", ["Thai"]], "RBjVu2fFv9NPkV8XD9R9yw": ["RBjVu2fFv9NPkV8XD9R9yw", ["Thai"]], "wEawMdWT7UtZjEmmMTBiGA": ["wEawMdWT7UtZjEmmMTBiGA", ["Thai"]], "QCpJlezYJnkZYNat-XYXYw": ["QCpJlezYJnkZYNat-XYXYw", ["Thai"]], "iUEvASoukxI6vrCYWYyK8g": ["iUEvASoukxI6vrCYWYyK8g", ["Thai"]], "feY7PgoRjCp2qReaIitRkQ": ["feY7PgoRjCp2qReaIitRkQ", ["Thai"]], "A_GbgtUSyGWpihHZOqMdwQ": ["A_GbgtUSyGWpihHZOqMdwQ", ["Thai"]], "oNN202L_XcNM-tuDHlgkfg": ["oNN202L_XcNM-tuDHlgkfg", ["Thai"]], "HnTcWZbZJzNAYO8YseQlSQ": ["HnTcWZbZJzNAYO8YseQlSQ", ["Thai"]], "1ctLdRJjP9m5QdL7ruYAzA": ["1ctLdRJjP9m5QdL7ruYAzA", ["Thai"]], "I4FWrwXDC91lsfQLXYSeXA": ["I4FWrwXDC91lsfQLXYSeXA", ["Thai"]], "qrydcGQpeDP_1oFvx3qOeg": ["qrydcGQpeDP_1oFvx3qOeg", ["Thai"]], "g7qtHQ_121mYWUdu3VWlrA": ["g7qtHQ_121mYWUdu3VWlrA", ["Thai", "Bars", "Tapas/Small Plates"]], "ykf5siP-2CXY3leFbeeabQ": ["ykf5siP-2CXY3leFbeeabQ", ["Vietnamese", "Sushi Bars", "Thai"]], "UkA3V8itzKuBGZ9c7y989w": ["UkA3V8itzKuBGZ9c7y989w", ["Thai", "Cocktail Bars"]], "n7LORZ0fGxPhOfdlHYREKQ": ["n7LORZ0fGxPhOfdlHYREKQ", ["Thai"]], "rCtsqHtOAOjZ7EUQDFRSbA": ["rCtsqHtOAOjZ7EUQDFRSbA", ["Thai", "Breakfast & Brunch", "Venues & Event Spaces"]], "2ZBEE_MJeRdLD1NLiNTnCQ": ["2ZBEE_MJeRdLD1NLiNTnCQ", ["Thai", "Seafood"]], "oyxk3hv9F7dGZGARmNDSYg": ["oyxk3hv9F7dGZGARmNDSYg", ["Thai", "Noodles"]], "3GMHPnrkFAcqffw3T7JSdQ": ["3GMHPnrkFAcqffw3T7JSdQ", ["Thai"]], "9IT7UsL-SGEz6ncR4oeJ9g": ["9IT7UsL-SGEz6ncR4oeJ9g", ["Thai"]], "_zRVdCfUcx1cwseFycSQdQ": ["_zRVdCfUcx1cwseFycSQdQ", ["Thai"]], "fRO4Fwe5uRAajMcTwLbVkA": ["fRO4Fwe5uRAajMcTwLbVkA", ["Thai", "Cocktail Bars"]], "Io54KD1yQK6M6BQc8WTAeA": ["Io54KD1yQK6M6BQc8WTAeA", ["Food Trucks", "Thai"]], "cegA4jf16vEt7NCQ7cpu2w": ["cegA4jf16vEt7NCQ7cpu2w", ["Thai"]], "0L03onqNwxWLrbb_FCK79A": ["0L03onqNwxWLrbb_FCK79A", ["Thai"]], "ucWrNKS65jUVK6ICUoHC8Q": ["ucWrNKS65jUVK6ICUoHC8Q", ["Thai"]], "jKDXlyPG-2rmcp9Ej6jPLA": ["jKDXlyPG-2rmcp9Ej6jPLA", ["Thai", "Desserts", "Soup"]], "IdHZfmpp8MmQ4_KZL2qXbg": ["IdHZfmpp8MmQ4_KZL2qXbg", ["Thai", "Noodles"]], "dVR5KHPMZoU9rQvxhY5Otw": ["dVR5KHPMZoU9rQvxhY5Otw", ["Thai"]], "nFszVPUX4tj-oarjfBO0nw": ["nFszVPUX4tj-oarjfBO0nw", ["Thai"]], "IiYRxMJLfLCsgifzRNvrtA": ["IiYRxMJLfLCsgifzRNvrtA", ["Thai", "Pan Asian", "Noodles"]], "58jCXglRFRn6qwZ_IxYb6A": ["58jCXglRFRn6qwZ_IxYb6A", ["Thai"]], "yCJHIM-PWl54K53ACOpoNg": ["yCJHIM-PWl54K53ACOpoNg", ["Thai"]], "jfnDwWBGK4JoWE5jbeKxSw": ["jfnDwWBGK4JoWE5jbeKxSw", ["Thai"]], "9VyMJICKGbC7Y5Ssq-Xk7w": ["9VyMJICKGbC7Y5Ssq-Xk7w", ["Thai"]], "ZlUU_DPlJTBLyUpBL2niKw": ["ZlUU_DPlJTBLyUpBL2niKw", ["Thai", "Cocktail Bars"]], "e64Y17DJgjotSz8B9gEI7Q": ["e64Y17DJgjotSz8B9gEI7Q", ["Thai", "Bars"]], "a-Bq_yXFVk2PptoWpmry3w": ["a-Bq_yXFVk2PptoWpmry3w", ["Thai", "Noodles"]], "hA5QUlrSjpxMZ90Kof0bgA": ["hA5QUlrSjpxMZ90Kof0bgA", ["Thai"]], "PPQSf_1JWkbjFHi1S0nSNA": ["PPQSf_1JWkbjFHi1S0nSNA", ["Thai"]], "Kyx9QFPJUzlC7dmM8SE1bw": ["Kyx9QFPJUzlC7dmM8SE1bw", ["Thai", "Asian Fusion", "Bars"]], "a5H9p1B6m6WPVjakPylvdA": ["a5H9p1B6m6WPVjakPylvdA", ["Thai", "Japanese", "Bars"]], "F_16U6tXkSSZYsjotzr-cA": ["F_16U6tXkSSZYsjotzr-cA", ["Thai"]], "Tmc90kL5jelJ2c9CiGzSFA": ["Tmc90kL5jelJ2c9CiGzSFA", ["Thai"]], "AILf_L7I9vJ2pyHmSo9v8Q": ["AILf_L7I9vJ2pyHmSo9v8Q", ["Asian Fusion", "Thai", "Vietnamese"]], "nxTEuWKzkK1tCF4LrhFSUQ": ["nxTEuWKzkK1tCF4LrhFSUQ", ["Filipino", "Thai", "Asian Fusion"]], "XgiG7K7ubHsj2JJ-c2sXnw": ["XgiG7K7ubHsj2JJ-c2sXnw", ["Thai"]], "inftQdKaEEiqQ323AlomXg": ["inftQdKaEEiqQ323AlomXg", ["Desserts", "Thai", "Noodles"]], "Wq9cARVEwOmoqfg41mNRNg": ["Wq9cARVEwOmoqfg41mNRNg", ["Thai", "Bars", "Beer, Wine & Spirits"]], "kXuubLd6s3GidpqU3psPdw": ["kXuubLd6s3GidpqU3psPdw", ["Thai"]], "LzyDj8z2CA03Jrs34L9Pgw": ["LzyDj8z2CA03Jrs34L9Pgw", ["Thai"]], "0GftSP2dRwEzujkv2VKIgA": ["0GftSP2dRwEzujkv2VKIgA", ["Chinese", "Malaysian", "Thai"]], "fgGRIM0b9JGIoNOAnHzROQ": ["fgGRIM0b9JGIoNOAnHzROQ", ["Thai", "Noodles"]], "T8WfkzuVi96qCpj1tWjlxw": ["T8WfkzuVi96qCpj1tWjlxw", ["Thai", "Cocktail Bars"]], "qtRPV9YANKcXU3OzcUUokw": ["qtRPV9YANKcXU3OzcUUokw", ["Thai", "Sushi Bars", "Asian Fusion"]], "qusZ-K5tzM1EyOa1IEWCHA": ["qusZ-K5tzM1EyOa1IEWCHA", ["Thai", "Asian Fusion", "Soup"]], "f7jZvRH-h76F4emzvKytaQ": ["f7jZvRH-h76F4emzvKytaQ", ["Thai"]], "56BXqZZ09-p1Lfw3ZDjV4A": ["56BXqZZ09-p1Lfw3ZDjV4A", ["Thai"]], "Nvhx093-K2xwHIZVnFstJw": ["Nvhx093-K2xwHIZVnFstJw", ["Thai"]], "414qtc1lNAI-HaJ-Gw9puA": ["414qtc1lNAI-HaJ-Gw9puA", ["Thai"]], "9FjGW7u1iTyFUDpJt-Ql9Q": ["9FjGW7u1iTyFUDpJt-Ql9Q", ["Thai"]], "T4xmuPYBmMhF48bfi9rkfA": ["T4xmuPYBmMhF48bfi9rkfA", ["Thai", "Noodles", "Comfort Food"]], "rhWaFGReGsmyWAojvGWQlQ": ["rhWaFGReGsmyWAojvGWQlQ", ["Thai"]], "e1jwvzY8hU642HSBZZATcw": ["e1jwvzY8hU642HSBZZATcw", ["Thai"]], "OPSCHpuBSthP7UwnMm0GSA": ["OPSCHpuBSthP7UwnMm0GSA", ["Thai", "Cocktail Bars"]], "QVWmn5jmy_TPmg0G71Dk5g": ["QVWmn5jmy_TPmg0G71Dk5g", ["Thai", "Cocktail Bars"]], "DguAGioaK6ZIAt_6kk93tA": ["DguAGioaK6ZIAt_6kk93tA", ["Thai"]], "tVB11pOiDhPWlt_o6ylMNg": ["tVB11pOiDhPWlt_o6ylMNg", ["Thai", "Seafood", "Chicken Wings"]], "l3aVYfTWVINXaNGxlMz0bQ": ["l3aVYfTWVINXaNGxlMz0bQ", ["Thai"]], "LIsCe_l7kUlv2cUs6AxNQQ": ["LIsCe_l7kUlv2cUs6AxNQQ", ["Thai", "Seafood", "Soup"]], "9HwsZNvviqdJYzFICHlDcQ": ["9HwsZNvviqdJYzFICHlDcQ", ["Asian Fusion", "Halal", "Thai"]], "4ak7lLxs6jopSjkMWJ8yKQ": ["4ak7lLxs6jopSjkMWJ8yKQ", ["Thai"]], "v5YA6gFdj1jwTpz0Kjpjqw": ["v5YA6gFdj1jwTpz0Kjpjqw", ["Thai", "Bubble Tea"]], "ri2YWZ2jMuxauAUA__4uvw": ["ri2YWZ2jMuxauAUA__4uvw", ["Thai"]], "1Fe4lCiMPNVhoEyjg92frA": ["1Fe4lCiMPNVhoEyjg92frA", ["Thai"]], "qnD3XDvYIrFh_FppNH90cA": ["qnD3XDvYIrFh_FppNH90cA", ["Thai"]], "1uuxUq-QrUYX-Zal9TvFFQ": ["1uuxUq-QrUYX-Zal9TvFFQ", ["Thai"]], "6ZZUTGtH25tLN1SiM029ig": ["6ZZUTGtH25tLN1SiM029ig", ["Thai"]], "BKMCAYb9EAivUm3p-vrC9w": ["BKMCAYb9EAivUm3p-vrC9w", ["Laotian"]], "GQRNgvRLY6OhPs8BYTTYUw": ["GQRNgvRLY6OhPs8BYTTYUw", ["Thai"]], "XixegGx6pdU_H0MWWqN1_w": ["XixegGx6pdU_H0MWWqN1_w", ["Thai", "Chicken Shop"]], "HyENSD29rcF_5iSFakhMSw": ["HyENSD29rcF_5iSFakhMSw", ["Thai"]], "pcVlzw0Id0MvP8MJYMRgJg": ["pcVlzw0Id0MvP8MJYMRgJg", ["Thai"]], "Fz5shOVBZ4CF5xUKTq5PqQ": ["Fz5shOVBZ4CF5xUKTq5PqQ", ["Vietnamese", "Soup", "Sandwiches"]], "R7mKCkD9ZZfeec92GW7esQ": ["R7mKCkD9ZZfeec92GW7esQ", ["Thai"]], "sinDhwX8Egru_3FCI7bhkw": ["sinDhwX8Egru_3FCI7bhkw", ["Thai", "Malaysian", "Singaporean"]], "pSSajdYNKTyAGV8-fk7fWQ": ["pSSajdYNKTyAGV8-fk7fWQ", ["Thai"]], "fcCF0Kh_RCbv6KSVlb-Seg": ["fcCF0Kh_RCbv6KSVlb-Seg", ["Thai", "Cocktail Bars"]], "n61FbfvTddHBXF5WKWjF4g": ["n61FbfvTddHBXF5WKWjF4g", ["Thai", "Noodles", "Cocktail Bars"]], "f_a1oO8-y2qorh_-K8xWHw": ["f_a1oO8-y2qorh_-K8xWHw", ["Thai"]], "7lhmzhkct9-blnuBAp_HVQ": ["7lhmzhkct9-blnuBAp_HVQ", ["Thai", "Vegetarian"]], "kI7XN2V8zi4aMypgitFg4w": ["kI7XN2V8zi4aMypgitFg4w", ["Thai"]], "1ubEg-rrSE8IWXl6lJzIGw": ["1ubEg-rrSE8IWXl6lJzIGw", ["Thai"]], "khvnn7cpiYSpe80ue5YLvg": ["khvnn7cpiYSpe80ue5YLvg", ["Thai"]], "jg5nc64wLYKwKAvz_lfMuA": ["jg5nc64wLYKwKAvz_lfMuA", ["Thai", "Noodles", "Asian Fusion"]], "n20BmzZ-KGd0RCKcPGRv1A": ["n20BmzZ-KGd0RCKcPGRv1A", ["Thai"]], "23NSOmpzzrJTfWmYk8Lp4A": ["23NSOmpzzrJTfWmYk8Lp4A", ["Thai", "Breakfast & Brunch", "Irish"]], "McU7XI3HoWFELTDaGc1SEw": ["McU7XI3HoWFELTDaGc1SEw", ["Vietnamese", "Thai", "Asian Fusion"]], "CpY77cDN1KS5EdiXMmWovw": ["CpY77cDN1KS5EdiXMmWovw", ["Thai"]], "nIS0a4W7CNDU57cVwUvi9A": ["nIS0a4W7CNDU57cVwUvi9A", ["Thai"]], "bF38ob3wxacTztdQLRS-Sg": ["bF38ob3wxacTztdQLRS-Sg", ["Thai", "Salad", "Soup"]], "4nwVzRCfWFGe6_Taqee4Cg": ["4nwVzRCfWFGe6_Taqee4Cg", ["Thai"]], "9UkHgv9R3LakP0vNj6DMIg": ["9UkHgv9R3LakP0vNj6DMIg", ["Thai"]], "X3T2rK-GrEgVUai-MeXAzg": ["X3T2rK-GrEgVUai-MeXAzg", ["Food Trucks", "Thai"]], "YQyzlr3GLDjl6fokymAhqA": ["YQyzlr3GLDjl6fokymAhqA", ["Thai", "Japanese"]], "g4EXxoV0z_TnyWF8h9xMKQ": ["g4EXxoV0z_TnyWF8h9xMKQ", ["Thai", "Vegan", "Vegetarian"]], "EbX_9tqAJs4gW51gZpOB7g": ["EbX_9tqAJs4gW51gZpOB7g", ["Malaysian", "Thai", "Halal"]], "m2_ZNFos5ugAwe8ft8eaEw": ["m2_ZNFos5ugAwe8ft8eaEw", ["Thai", "Hainan"]], "IGjdEM0s4WfOYrMSzO6q9Q": ["IGjdEM0s4WfOYrMSzO6q9Q", ["Thai"]], "OR9oqAJW-U5ZnqhwH12Nuw": ["OR9oqAJW-U5ZnqhwH12Nuw", ["Thai", "Coffee & Tea"]], "oS1e-zZ_qzZNIUEp3FYHhQ": ["oS1e-zZ_qzZNIUEp3FYHhQ", ["Thai"]], "sljnE3uoRUmM7aW5f1I3Ug": ["sljnE3uoRUmM7aW5f1I3Ug", ["Thai"]], "v3qL3KqFJYuS_3rCsgpuXQ": ["v3qL3KqFJYuS_3rCsgpuXQ", ["Thai"]], "B9Mbi12NpBJkZcRtQNtMBA": ["B9Mbi12NpBJkZcRtQNtMBA", ["Malaysian"]], "QYr9EO-2FmdpOVUjOyNjgg": ["QYr9EO-2FmdpOVUjOyNjgg", ["Thai"]], "7pWF8zJ26goQRqdlzvW9Qw": ["7pWF8zJ26goQRqdlzvW9Qw", ["Thai"]], "RdGWCbcxA79G1ZMPVL3SGQ": ["RdGWCbcxA79G1ZMPVL3SGQ", ["Thai", "Lounges", "Noodles"]], "Ur1VZwMZ8Qbd6KLpiid7lg": ["Ur1VZwMZ8Qbd6KLpiid7lg", ["Thai"]], "4M-nT45SdA119-lcJg9c9A": ["4M-nT45SdA119-lcJg9c9A", ["Thai"]], "W03i9B7wZn2B5p9E_Yn5nw": ["W03i9B7wZn2B5p9E_Yn5nw", ["Thai"]], "UO4kyXfdQIlAhM-TRgM9cw": ["UO4kyXfdQIlAhM-TRgM9cw", ["Thai", "Desserts"]], "SBy46BviyBKowPjbTjDsHQ": ["SBy46BviyBKowPjbTjDsHQ", ["Thai"]], "5ZjNZd3Yg0jOkJ9WRx1r6g": ["5ZjNZd3Yg0jOkJ9WRx1r6g", ["Thai", "Noodles", "Soup"]], "EAkIy8TKrW4yPPDCZyP-Cw": ["EAkIy8TKrW4yPPDCZyP-Cw", ["Food Trucks", "Thai"]], "9WgsvzaiXNAmmQGD0uQxFQ": ["9WgsvzaiXNAmmQGD0uQxFQ", ["Thai", "Salad"]], "dqjko5ndMGayALuhwq3ghQ": ["dqjko5ndMGayALuhwq3ghQ", ["Thai", "Noodles"]], "uazg6WhYVOw3jhWCG_MDBg": ["uazg6WhYVOw3jhWCG_MDBg", ["Thai", "Seafood", "Noodles"]], "M-odQWSEfsR2mVEw7nKG-g": ["M-odQWSEfsR2mVEw7nKG-g", ["Asian Fusion", "Malaysian", "Chinese"]], "toykv8K0yg8qtvZSXRQ5bg": ["toykv8K0yg8qtvZSXRQ5bg", ["Thai"]], "yA29ur97O7B6kYr1g5IoAw": ["yA29ur97O7B6kYr1g5IoAw", ["Thai"]], "wyjtGsW5NeVDknGQWnIPAQ": ["wyjtGsW5NeVDknGQWnIPAQ", ["Asian Fusion"]], "siAb_uf13RIYW52O-auTpQ": ["siAb_uf13RIYW52O-auTpQ", ["Thai"]], "_7Maf5WG682E7R-EHSz18w": ["_7Maf5WG682E7R-EHSz18w", ["Thai", "Coffee & Tea", "Noodles"]], "8-dc942sz-prIeepAkHLJA": ["8-dc942sz-prIeepAkHLJA", ["Thai"]], "4mzogOLOVDPBDVTO4cz9fA": ["4mzogOLOVDPBDVTO4cz9fA", ["Thai"]], "2AcDHuatOFXhqJDedZwGiA": ["2AcDHuatOFXhqJDedZwGiA", ["Thai"]], "bjf8vmAIrdPo1aHoaYPkBw": ["bjf8vmAIrdPo1aHoaYPkBw", ["Thai", "Noodles"]], "jMb34zhfkqoW866F10hf1Q": ["jMb34zhfkqoW866F10hf1Q", ["Thai"]], "33ry5dmopDOElU7zf1Sn2w": ["33ry5dmopDOElU7zf1Sn2w", ["Thai"]], "zENn0_yDJEdLoHyivXb2xw": ["zENn0_yDJEdLoHyivXb2xw", ["Thai"]], "IYwz7ck1OZCoZqW0F31pLg": ["IYwz7ck1OZCoZqW0F31pLg", ["Thai", "Ramen", "Asian Fusion"]], "ZfuZ2byArGq-5j8zX8Afeg": ["ZfuZ2byArGq-5j8zX8Afeg", ["Sushi Bars", "Japanese", "Thai"]], "1sEr-BDi2LD6HH6K960pfQ": ["1sEr-BDi2LD6HH6K960pfQ", ["Thai"]], "59oP8zLjQLPY0Dyh004HSQ": ["59oP8zLjQLPY0Dyh004HSQ", ["Vietnamese"]], "RnQjRZ9MJrBN9SKiIv3i-A": ["RnQjRZ9MJrBN9SKiIv3i-A", ["Thai"]], "TUoya6mwmxr0Zpr8oZSXlg": ["TUoya6mwmxr0Zpr8oZSXlg", ["Thai"]], "EjuI8hyZO4jREWj3BTh8gw": ["EjuI8hyZO4jREWj3BTh8gw", ["Food Trucks", "Hainan", "Thai"]], "_ArDQIKj5qHgmwNnnIaIIg": ["_ArDQIKj5qHgmwNnnIaIIg", ["Thai", "Seafood", "Vegan"]], "-5npn9NRmOun7VUVLZpjyw": ["-5npn9NRmOun7VUVLZpjyw", ["Thai", "Chicken Shop", "Chicken Wings"]], "qNe3r33f17z1v10iEiB4DA": ["qNe3r33f17z1v10iEiB4DA", ["Thai"]], "RrPIJvmje1qb9iaYd6jH0g": ["RrPIJvmje1qb9iaYd6jH0g", ["Thai", "Desserts", "Seafood"]], "mpD_kUFo8POQDLoLgRSfCg": ["mpD_kUFo8POQDLoLgRSfCg", ["Thai"]], "iPaule2uCieebZk0rVFG1w": ["iPaule2uCieebZk0rVFG1w", ["Thai"]], "TU_BU9HLflYI2xlyqVQdRA": ["TU_BU9HLflYI2xlyqVQdRA", ["Asian Fusion"]], "bpeeh-kkay0ZE7mGXsCVKQ": ["bpeeh-kkay0ZE7mGXsCVKQ", ["Japanese", "Chinese", "Thai"]], "fZhPkKCYGWjEDgRZCNRnfg": ["fZhPkKCYGWjEDgRZCNRnfg", ["Noodles", "Thai", "Vegetarian"]], "Eyn7hQENF8R9DrBwBHO6lQ": ["Eyn7hQENF8R9DrBwBHO6lQ", ["Bubble Tea", "Cafes", "Thai"]], "DEoUnmEnguWiwlDh3CFm1A": ["DEoUnmEnguWiwlDh3CFm1A", ["Thai"]], "xRvMOTMzDrMfyAWbYhkA8A": ["xRvMOTMzDrMfyAWbYhkA8A", ["Thai"]], "-YazuZbXAM_NOny8LpLQpQ": ["-YazuZbXAM_NOny8LpLQpQ", ["Thai", "Seafood", "Salad"]], "B0e6kXT0doU-n6EvMVGzQQ": ["B0e6kXT0doU-n6EvMVGzQQ", ["Thai", "Cocktail Bars", "Asian Fusion"]], "oO_X1H5Lxo8sNykx6azLVQ": ["oO_X1H5Lxo8sNykx6azLVQ", ["Thai"]], "9v4l7pz4J709z0mkqUpQbw": ["9v4l7pz4J709z0mkqUpQbw", ["Thai", "Bubble Tea", "Noodles"]], "dnCRiUZWgu5ZI4Q-Z-az6Q": ["dnCRiUZWgu5ZI4Q-Z-az6Q", ["Thai", "Salad", "Soup"]], "ebhDBwRzD--eoiYcO8M18g": ["ebhDBwRzD--eoiYcO8M18g", ["Thai", "Laotian"]], "zYIKxE7eKeglXweoABjSwg": ["zYIKxE7eKeglXweoABjSwg", ["Thai"]], "7DnZWIn1Dcsvq-_pIXXFZQ": ["7DnZWIn1Dcsvq-_pIXXFZQ", ["Asian Fusion", "Korean", "Tapas/Small Plates"]], "OVAV0k2O1kqeuRFyt95qzg": ["OVAV0k2O1kqeuRFyt95qzg", ["Thai", "Noodles"]], "ZUsSH8xPciM8EnQxqlKXCg": ["ZUsSH8xPciM8EnQxqlKXCg", ["Thai"]], "od-UsU-zZx29CWLhq-eong": ["od-UsU-zZx29CWLhq-eong", ["Thai"]], "l_gQf_4NgPMJcx2OkjsMfg": ["l_gQf_4NgPMJcx2OkjsMfg", ["Thai"]], "Xst2vGND8hy44VOmbLG3kQ": ["Xst2vGND8hy44VOmbLG3kQ", ["Thai"]], "liGIz8CzhyS1udx1aefjng": ["liGIz8CzhyS1udx1aefjng", ["Thai"]], "jc_XQPbSCwMHsXLfinXA6A": ["jc_XQPbSCwMHsXLfinXA6A", ["Thai", "Asian Fusion"]], "S2b4gAh3Sr1sbNGaTna1Xw": ["S2b4gAh3Sr1sbNGaTna1Xw", ["Thai"]], "0nvJPFqv5VD-Bf2WtzD0rA": ["0nvJPFqv5VD-Bf2WtzD0rA", ["Thai", "Coffee & Tea", "Bubble Tea"]], "ACuZg-9J4bE6hRgu8p501g": ["ACuZg-9J4bE6hRgu8p501g", ["Thai", "Food Trucks"]], "SoEQRDUNYDZPVSSIhTOG6A": ["SoEQRDUNYDZPVSSIhTOG6A", ["Thai", "Cocktail Bars"]], "97j_C4P6VqRIHz21usaFig": ["97j_C4P6VqRIHz21usaFig", ["Thai", "Noodles"]], "ColGPMmJOa6YD44fjS6wfg": ["ColGPMmJOa6YD44fjS6wfg", ["Thai"]], "gBoqjD5MTJuGx65QjAhJGg": ["gBoqjD5MTJuGx65QjAhJGg", ["Thai"]], "nxUs6svpNSL0wAwAA2F34w": ["nxUs6svpNSL0wAwAA2F34w", ["Thai"]], "_pZk7XbpyqTSfHBllTGAEg": ["_pZk7XbpyqTSfHBllTGAEg", ["Thai"]], "rehmlZmUNL2AthW-VTXJJQ": ["rehmlZmUNL2AthW-VTXJJQ", ["Thai"]], "cmssS5DPbF6Yv-EJdKVm_w": ["cmssS5DPbF6Yv-EJdKVm_w", ["Thai"]], "RkPakW9XloEm-QB0eNlHmw": ["RkPakW9XloEm-QB0eNlHmw", ["Indian", "Thai"]], "CFIOL_GmkAuJyz3fKc7WYg": ["CFIOL_GmkAuJyz3fKc7WYg", ["Thai"]], "GSOwJ5Gr8X4eGbkIjCzMWA": ["GSOwJ5Gr8X4eGbkIjCzMWA", ["Thai"]], "S14Ewv4-h0-EtfMeYMbrzg": ["S14Ewv4-h0-EtfMeYMbrzg", ["Thai"]], "4xQ7ZLWHFALOmJJURDOCUw": ["4xQ7ZLWHFALOmJJURDOCUw", ["Noodles", "Thai"]], "YGssrvI4BAa4WS21Glnqjg": ["YGssrvI4BAa4WS21Glnqjg", ["Thai"]], "gJMMX5Ip4AsulbzxMZgdYg": ["gJMMX5Ip4AsulbzxMZgdYg", ["Thai", "Asian Fusion", "Chicken Wings"]], "BFe80peJUjkBYMliFoPu9Q": ["BFe80peJUjkBYMliFoPu9Q", ["Thai", "Noodles", "Asian Fusion"]], "nu239sXQUGjcGFhZ3AdJmQ": ["nu239sXQUGjcGFhZ3AdJmQ", ["Thai"]], "D-gd1Gb_Nmc2MN6G0KANMg": ["D-gd1Gb_Nmc2MN6G0KANMg", ["Thai"]], "MD-GiizNpmFbuDIdKGzXnA": ["MD-GiizNpmFbuDIdKGzXnA", ["Thai", "Vietnamese"]], "E7GJXN50VhreutDji_H_Dg": ["E7GJXN50VhreutDji_H_Dg", ["Thai"]], "cugwo9ncnGnH_Chu-P-iAw": ["cugwo9ncnGnH_Chu-P-iAw", ["Thai"]], "tjILxkIZKcppgew6NwIngQ": ["tjILxkIZKcppgew6NwIngQ", ["Thai"]], "XNkC1vJmLOI8NRR3Jl_vyQ": ["XNkC1vJmLOI8NRR3Jl_vyQ", ["Thai"]], "pjCLHrmXcfb2BLaZS1fXsA": ["pjCLHrmXcfb2BLaZS1fXsA", ["Thai"]], "7hyQqnnAisSL-nfIWCPziQ": ["7hyQqnnAisSL-nfIWCPziQ", ["Asian Fusion", "Chinese", "Thai"]], "zJ6-ZCrtJA943nsVl2l8gQ": ["zJ6-ZCrtJA943nsVl2l8gQ", ["Thai"]], "63e2dDq5WCbpaBlercQllg": ["63e2dDq5WCbpaBlercQllg", ["Thai"]], "-wnwpVjmtkHzvn7jPcLM-g": ["-wnwpVjmtkHzvn7jPcLM-g", ["Thai", "Halal"]], "FXFQJmhK6elesopXdhjvFQ": ["FXFQJmhK6elesopXdhjvFQ", ["Japanese", "Sushi Bars", "Asian Fusion"]], "fePu8xy0ir_ikZcS_vVSBA": ["fePu8xy0ir_ikZcS_vVSBA", ["Japanese", "Thai", "Cocktail Bars"]], "WOrCzAOgs50Wf-dlnHrzDw": ["WOrCzAOgs50Wf-dlnHrzDw", ["Thai"]], "YIgBb6jb_KV0-nbYZ1oPig": ["YIgBb6jb_KV0-nbYZ1oPig", ["Thai"]], "W9t_RWcisBoXMS0iAl7frQ": ["W9t_RWcisBoXMS0iAl7frQ", ["Thai", "Desserts", "Salad"]], "fe9aDWC5giHgcuKjqSr_gQ": ["fe9aDWC5giHgcuKjqSr_gQ", ["Thai"]], "a23bfZBVjIhV32Em4hKHAA": ["a23bfZBVjIhV32Em4hKHAA", ["Thai", "American (New)"]], "GKZa6xX1ZctdDTLDyfGBHw": ["GKZa6xX1ZctdDTLDyfGBHw", ["Thai", "Dim Sum", "Asian Fusion"]], "AAXX-WkDd1CW3_GgIVivvw": ["AAXX-WkDd1CW3_GgIVivvw", ["Thai"]], "LvmDVd1OlRGFdtY4RH2iSQ": ["LvmDVd1OlRGFdtY4RH2iSQ", ["Thai"]], "Tgz0bhjz-api1CGS_ANFoQ": ["Tgz0bhjz-api1CGS_ANFoQ", ["Thai", "Ice Cream & Frozen Yogurt", "Desserts"]], "I_YPy_YRtZFyWOSWs-gv4A": ["I_YPy_YRtZFyWOSWs-gv4A", ["Food Trucks", "Thai", "Caterers"]], "nI1UYDCYUTt23TpGxqnLKg": ["nI1UYDCYUTt23TpGxqnLKg", ["Chinese", "Bars", "Asian Fusion"]], "vm4fi1M_fxqIdIkHAgtBaQ": ["vm4fi1M_fxqIdIkHAgtBaQ", ["Thai", "Noodles", "Dim Sum"]], "xFp3xSQ43J-i7nmJfNBsZA": ["xFp3xSQ43J-i7nmJfNBsZA", ["Sushi Bars", "Ramen", "Asian Fusion"]], "yzbIUIeDuSH58WgK32J7Fw": ["yzbIUIeDuSH58WgK32J7Fw", ["Thai", "Noodles", "Seafood"]], "MxMWPaC30sRkPKit_Omz2A": ["MxMWPaC30sRkPKit_Omz2A", ["Thai"]], "PyaeHq_UAu6nazGiy0XAnw": ["PyaeHq_UAu6nazGiy0XAnw", ["Vietnamese", "Thai"]], "Z7uV9jqrj9GkSws1cz06cg": ["Z7uV9jqrj9GkSws1cz06cg", ["Thai", "Salad", "Soup"]], "4qNjla0etKdN6WCTphBVug": ["4qNjla0etKdN6WCTphBVug", ["Noodles"]], "UFMXc5B0i_IetI-f8Dpb5A": ["UFMXc5B0i_IetI-f8Dpb5A", ["Thai"]], "RwEs6AvU5Cxp_ENodsgxHw": ["RwEs6AvU5Cxp_ENodsgxHw", ["Thai"]], "cvJ39wrAYnquWuMhfFAS2w": ["cvJ39wrAYnquWuMhfFAS2w", ["Thai", "Noodles", "Beer Bar"]], "HLDKZXsi7TQ0P3rS2wd-UQ": ["HLDKZXsi7TQ0P3rS2wd-UQ", ["Vietnamese", "Thai"]], "0fjab0vzFgIQ-FKzjFR7JQ": ["0fjab0vzFgIQ-FKzjFR7JQ", ["Thai"]], "utg1E8cea7vY5VuDyoOthA": ["utg1E8cea7vY5VuDyoOthA", ["Thai"]], "ybczZr7m8jZtGe0qDPXW5w": ["ybczZr7m8jZtGe0qDPXW5w", ["Thai"]], "6wJOojpF2c4lLeBNbTBB0A": ["6wJOojpF2c4lLeBNbTBB0A", ["Asian Fusion", "Thai", "Pan Asian"]], "-smadDWqhGLeN3Dv8uGrJg": ["-smadDWqhGLeN3Dv8uGrJg", ["Vietnamese"]], "kLvz8Erjz296xNC4huUxfQ": ["kLvz8Erjz296xNC4huUxfQ", ["Thai"]], "sDxRkhk9A2nDT2aKENsAww": ["sDxRkhk9A2nDT2aKENsAww", ["Thai", "Venues & Event Spaces"]], "2wxwpJs4ZrgniJH6Cst-bA": ["2wxwpJs4ZrgniJH6Cst-bA", ["Thai"]], "CY1lJBQatCNo4-_ljlS1rA": ["CY1lJBQatCNo4-_ljlS1rA", ["Asian Fusion", "Thai"]], "VMDmMIWR059HKMp_Mj3Msw": ["VMDmMIWR059HKMp_Mj3Msw", ["Thai"]], "ipxeCjihDqXTMkuPe-CQ4A": ["ipxeCjihDqXTMkuPe-CQ4A", ["Thai"]], "lI91u68v2xTdE70lyioKAg": ["lI91u68v2xTdE70lyioKAg", ["Thai"]], "pREotiEdCIV1GKSp_pLgNA": ["pREotiEdCIV1GKSp_pLgNA", ["Thai"]], "RSZITLOyKCsvCKLJNiE3Hg": ["RSZITLOyKCsvCKLJNiE3Hg", ["Thai"]], "XF9MChLaOvtaFV-bReLBqQ": ["XF9MChLaOvtaFV-bReLBqQ", ["Thai", "Cantonese"]], "CgYWuNH0UHd5vp2vGgKflw": ["CgYWuNH0UHd5vp2vGgKflw", ["Noodles", "Asian Fusion"]], "cADZEB7qFr-8I3fVxHbM1A": ["cADZEB7qFr-8I3fVxHbM1A", ["Thai"]], "LDScBEu3splSQlhGBEH2hg": ["LDScBEu3splSQlhGBEH2hg", ["Taiwanese", "Coffee & Tea", "Asian Fusion"]], "StFf9fVnAlhwrUWan0C4Ww": ["StFf9fVnAlhwrUWan0C4Ww", ["Thai", "Noodles"]], "Ut4N7Fxikkxi214fy5Qo2w": ["Ut4N7Fxikkxi214fy5Qo2w", ["Thai"]], "w2XTAF56oI2ywMGc9W6SQA": ["w2XTAF56oI2ywMGc9W6SQA", ["Thai"]], "W1L0UB1MvlhvkKTF43emSA": ["W1L0UB1MvlhvkKTF43emSA", ["Thai", "Hot Pot"]], "mFWOB5TqSF2MSKuACnt3kw": ["mFWOB5TqSF2MSKuACnt3kw", ["Thai"]], "WFx1VcopQGjW7jbERZUUbA": ["WFx1VcopQGjW7jbERZUUbA", ["Thai"]], "V-rY0hlPjAghV14jOlVUiQ": ["V-rY0hlPjAghV14jOlVUiQ", ["Asian Fusion", "Thai", "Sushi Bars"]], "Ge9wqsI72Mvk375CPvXurw": ["Ge9wqsI72Mvk375CPvXurw", ["Thai", "Hainan", "Food Trucks"]], "ybPMdh4XiTTwLWOMUXdwlw": ["ybPMdh4XiTTwLWOMUXdwlw", ["Thai"]], "zdB4nA0Xpyxhi5oIt6wVng": ["zdB4nA0Xpyxhi5oIt6wVng", ["Sandwiches", "Vietnamese", "Asian Fusion"]], "ZGKdgFAGOL6NOPXPrBkhzA": ["ZGKdgFAGOL6NOPXPrBkhzA", ["Thai"]], "zRQNaDUoWTInc2tqndSJVA": ["zRQNaDUoWTInc2tqndSJVA", ["Thai"]], "cWodGgBljJUVp9QQiPt3yQ": ["cWodGgBljJUVp9QQiPt3yQ", ["Thai"]], "eQzQo6XWLHstH5A2IpwXPQ": ["eQzQo6XWLHstH5A2IpwXPQ", ["Thai"]], "rvI-gvqsWy_HmunwUsjmGg": ["rvI-gvqsWy_HmunwUsjmGg", ["Thai", "Noodles", "Bars"]], "nybFUH8FR1Dcn3DwYxe__Q": ["nybFUH8FR1Dcn3DwYxe__Q", ["Thai"]], "FL7aHCbKMDSpchQS1KucHQ": ["FL7aHCbKMDSpchQS1KucHQ", ["Thai", "Lounges", "Karaoke"]], "mbj9MMuTsOMxKPyjQ3F0Mw": ["mbj9MMuTsOMxKPyjQ3F0Mw", ["Thai"]], "qtDKasElRD_CPw7HnIOXHA": ["qtDKasElRD_CPw7HnIOXHA", ["Thai", "Food Stands"]], "7rxA2Ne0ON6iHFBJ6TJDIg": ["7rxA2Ne0ON6iHFBJ6TJDIg", ["Thai"]], "7ztNVUAfAyJXQLGU9BkPiw": ["7ztNVUAfAyJXQLGU9BkPiw", ["Thai"]], "Ri0hq80RV6yrPDHmW4Gu3g": ["Ri0hq80RV6yrPDHmW4Gu3g", ["Thai"]], "2-z6dRAkKupCyz1LF251pQ": ["2-z6dRAkKupCyz1LF251pQ", ["Thai"]], "6i14XPO7y3aGAvgdxRjVEg": ["6i14XPO7y3aGAvgdxRjVEg", ["Thai", "Soup"]], "OWv-LobTHp8MWWZBT2mtIg": ["OWv-LobTHp8MWWZBT2mtIg", ["Thai"]], "1svF14BUYt_Wc0XA3nMxdw": ["1svF14BUYt_Wc0XA3nMxdw", ["Thai"]], "tk_hI5v8KufzFaIP57_57g": ["tk_hI5v8KufzFaIP57_57g", ["Thai"]], "0VGn3bLaUG7lhM5WwkMTCA": ["0VGn3bLaUG7lhM5WwkMTCA", ["Thai"]], "5DwGICd6TkAnvO6YNeYp0Q": ["5DwGICd6TkAnvO6YNeYp0Q", ["Thai", "Vegetarian", "Asian Fusion"]], "dyFvVNDumWZgXtV3GlK8vw": ["dyFvVNDumWZgXtV3GlK8vw", ["Thai", "Noodles", "Cocktail Bars"]], "lBYqc4_DP28wXTLVL--sYQ": ["lBYqc4_DP28wXTLVL--sYQ", ["Thai", "Noodles", "Soup"]], "eHSu9NDWPJ3BvQDmPEJpfQ": ["eHSu9NDWPJ3BvQDmPEJpfQ", ["Asian Fusion", "Sushi Bars", "Thai"]], "sSkLiIMnOBaN-XKwV5r3Cg": ["sSkLiIMnOBaN-XKwV5r3Cg", ["Thai", "Cocktail Bars"]], "ZQHZAvw1jvNznbo1wFb_4w": ["ZQHZAvw1jvNznbo1wFb_4w", ["Thai"]], "3KlWyCJ2BikxwcEb0-O4Ww": ["3KlWyCJ2BikxwcEb0-O4Ww", ["Thai"]], "1BJo1JcwYHUuk-UfJLEwUQ": ["1BJo1JcwYHUuk-UfJLEwUQ", ["Thai"]], "HDoJIH-qW9FqJ5WB-bKTqA": ["HDoJIH-qW9FqJ5WB-bKTqA", ["Asian Fusion", "Japanese", "Korean"]], "G6qaJ9pIfUbf-uCIFZQ3cg": ["G6qaJ9pIfUbf-uCIFZQ3cg", ["Thai", "Food Stands"]], "io73CG07m5_w9TP3_rl8DQ": ["io73CG07m5_w9TP3_rl8DQ", ["Thai"]], "W_fpRJ7A10bTzSlreWtOPA": ["W_fpRJ7A10bTzSlreWtOPA", ["Thai"]], "AekKkXTaCXlYp95KrxlesA": ["AekKkXTaCXlYp95KrxlesA", ["Thai"]], "VpInBiE272MaN1Hi0DA-Zw": ["VpInBiE272MaN1Hi0DA-Zw", ["Asian Fusion", "Sushi Bars"]], "Bh0Rxd4Yi21luny0S95GaQ": ["Bh0Rxd4Yi21luny0S95GaQ", ["Sushi Bars", "Asian Fusion", "Thai"]], "LQ8ITaZIbaiQ8pHPOx5i6w": ["LQ8ITaZIbaiQ8pHPOx5i6w", ["Ice Cream & Frozen Yogurt", "Thai"]], "neQM053ovAOrf1sVSAPI9w": ["neQM053ovAOrf1sVSAPI9w", ["Asian Fusion", "Tea Rooms", "Chinese"]], "NBTIngamQxYAx2UEabDJNA": ["NBTIngamQxYAx2UEabDJNA", ["Vietnamese"]], "Xh-pnPzmUOnjyDE2bTGv5w": ["Xh-pnPzmUOnjyDE2bTGv5w", ["Sushi Bars", "Thai"]], "DDrLKyZodnd9KbOWq4F5nw": ["DDrLKyZodnd9KbOWq4F5nw", ["Thai"]], "aZrTVBKQzlcFo_KwzhIw-A": ["aZrTVBKQzlcFo_KwzhIw-A", ["Thai", "Vietnamese", "Sandwiches"]], "Di9rtHNxQvNQPVi_1JgDsQ": ["Di9rtHNxQvNQPVi_1JgDsQ", ["Thai"]], "i6H4hcjBSarJRVaieOZ2fw": ["i6H4hcjBSarJRVaieOZ2fw", ["Thai", "Desserts", "Salad"]], "3Qpi419I29t3sCHMzC_h-g": ["3Qpi419I29t3sCHMzC_h-g", ["Thai", "Chinese"]], "h4wpGRaMue8FSbcMcz1qPg": ["h4wpGRaMue8FSbcMcz1qPg", ["Thai"]], "3pOAiE7W7nDEeVFNy_vmfw": ["3pOAiE7W7nDEeVFNy_vmfw", ["Thai"]], "SOrQnn_dsHIFpmW5HTCFCw": ["SOrQnn_dsHIFpmW5HTCFCw", ["Thai"]], "fJW2CdsqXrKRtaHqoZoeHg": ["fJW2CdsqXrKRtaHqoZoeHg", ["Thai", "Vietnamese"]], "Ve_iFpnhL8zN789ZL2jnxQ": ["Ve_iFpnhL8zN789ZL2jnxQ", ["Thai", "Vegan", "Noodles"]], "TuGFxspYWd0smugwUeN9sA": ["TuGFxspYWd0smugwUeN9sA", ["Cafes", "Wine Bars", "Thai"]], "EzyjRrhRpt_NR7wIwqm_Rg": ["EzyjRrhRpt_NR7wIwqm_Rg", ["Thai"]], "JX5QkNfMd-jP-Nz5iQ_QeA": ["JX5QkNfMd-jP-Nz5iQ_QeA", ["Thai", "Halal"]], "1vZzyvUqDwZyaBqFk4zkKA": ["1vZzyvUqDwZyaBqFk4zkKA", ["Thai"]], "CODADSsXEq7PsdV7BncjFw": ["CODADSsXEq7PsdV7BncjFw", ["Thai"]], "pXxBeKXDgcNSioo-3ysMcg": ["pXxBeKXDgcNSioo-3ysMcg", ["Chinese", "Thai"]], "shHhP5lfZwrAYFL3K04_lg": ["shHhP5lfZwrAYFL3K04_lg", ["Thai", "Ramen", "Izakaya"]], "_Ki5XZTB8mL9RDYGj7KP0w": ["_Ki5XZTB8mL9RDYGj7KP0w", ["Thai"]], "S2b7VCymh4W4iLveuRnOgg": ["S2b7VCymh4W4iLveuRnOgg", ["Vietnamese", "Thai"]], "EEf5KB5wx340TY7QwDKIqQ": ["EEf5KB5wx340TY7QwDKIqQ", ["Sushi Bars", "Thai"]], "m2Zsy2UAkcDf0cRzk2Yoqw": ["m2Zsy2UAkcDf0cRzk2Yoqw", ["Vietnamese"]], "mU1ctN2chR3U3__d_Zjcng": ["mU1ctN2chR3U3__d_Zjcng", ["Thai"]], "C2o3Iw-DXjoUJFgQIbiqkQ": ["C2o3Iw-DXjoUJFgQIbiqkQ", ["Vietnamese", "French", "Asian Fusion"]], "DYOyC7JQ0DBCY59b7HKb6A": ["DYOyC7JQ0DBCY59b7HKb6A", ["Thai", "Food Trucks"]], "DShGW7JgORh99PYS3C6L1Q": ["DShGW7JgORh99PYS3C6L1Q", ["Pop-Up Restaurants", "Thai", "Pizza"]], "rL2wuxtLAQWPDZ0IbOHjxA": ["rL2wuxtLAQWPDZ0IbOHjxA", ["Thai"]], "v2dtG37r1ThqtfEfiFsAUg": ["v2dtG37r1ThqtfEfiFsAUg", ["Korean", "Chinese", "Asian Fusion"]], "Ha8rj8csvWA-ZFPck93yug": ["Ha8rj8csvWA-ZFPck93yug", ["Vegetarian", "Salad", "Vegan"]], "iTke4ZsI0WyAHD6fmAtRLA": ["iTke4ZsI0WyAHD6fmAtRLA", ["Thai", "Malaysian"]], "SkYcO8FaqYgoP-66g58OMw": ["SkYcO8FaqYgoP-66g58OMw", ["Thai"]], "hnBgmEQsJgRhY3VvWnwkfA": ["hnBgmEQsJgRhY3VvWnwkfA", ["Thai", "Malaysian", "Asian Fusion"]], "Xf5xrD2qZb8_UCOiPbBq3Q": ["Xf5xrD2qZb8_UCOiPbBq3Q", ["Vietnamese"]], "7rTl_d-dqlK5dGG31ogSBg": ["7rTl_d-dqlK5dGG31ogSBg", ["Indian", "Thai", "Chinese"]], "QMjwVS8CAJ72T5PLiSx3GA": ["QMjwVS8CAJ72T5PLiSx3GA", ["Vietnamese", "Thai"]], "0A2lgMwqKCsr95qZtd4mKA": ["0A2lgMwqKCsr95qZtd4mKA", ["Thai", "Salad", "Noodles"]], "KIERtmoOTz7r103MWw08nA": ["KIERtmoOTz7r103MWw08nA", ["Thai", "Cafes"]], "P4iD0CGBWbLAErbWP9uIDQ": ["P4iD0CGBWbLAErbWP9uIDQ", ["French", "American (New)", "Asian Fusion"]], "RmQOUUkwHDhuuh9Y6XzLsQ": ["RmQOUUkwHDhuuh9Y6XzLsQ", ["Thai", "American (Traditional)", "Comfort Food"]], "3nATnhLyWRvbUGRwK2zdXQ": ["3nATnhLyWRvbUGRwK2zdXQ", ["Vietnamese", "Thai", "Noodles"]], "r2JVKalbucGf2nryywuL2w": ["r2JVKalbucGf2nryywuL2w", ["Malaysian", "Singaporean"]], "ce_1B5fkrAxsVBHMcQeK6g": ["ce_1B5fkrAxsVBHMcQeK6g", ["Thai", "Food Stands"]], "B9UfgHgm5-hOErK8-54EsA": ["B9UfgHgm5-hOErK8-54EsA", ["Thai"]], "V58g7E1AHkuTchTVyLQuYQ": ["V58g7E1AHkuTchTVyLQuYQ", ["Vietnamese", "Asian Fusion"]], "8Jz2IfS-BGCm1GniqJVe2A": ["8Jz2IfS-BGCm1GniqJVe2A", ["Sushi Bars", "Thai", "Asian Fusion"]], "kiKUF11kNgEnM__P11nrig": ["kiKUF11kNgEnM__P11nrig", ["Coffee & Tea", "Desserts", "Thai"]], "CvSOAN2WWzLRGND4vN1xtA": ["CvSOAN2WWzLRGND4vN1xtA", ["Asian Fusion", "Japanese", "Thai"]], "gr3wUszE1972q0GBkmwEXQ": ["gr3wUszE1972q0GBkmwEXQ", ["Thai"]], "HzJP6ICu_Naf5R0swzd-dg": ["HzJP6ICu_Naf5R0swzd-dg", ["Thai"]], "AeNU0DYNtYDVPGnWAIh-0Q": ["AeNU0DYNtYDVPGnWAIh-0Q", ["Asian Fusion", "Fast Food"]], "ftB-68pWfv2xl3LTDYocNg": ["ftB-68pWfv2xl3LTDYocNg", ["Thai"]], "U7IbB48W9CiUDb0NA5Jn7Q": ["U7IbB48W9CiUDb0NA5Jn7Q", ["Thai"]], "tx-gxkns4uFyve7Eu5mYKA": ["tx-gxkns4uFyve7Eu5mYKA", ["Thai"]], "s-UAKra4P0sFE9ylXlwwfA": ["s-UAKra4P0sFE9ylXlwwfA", ["Vietnamese", "Thai", "Asian Fusion"]], "mzS1uMzO6hF1wlIoTg8d1g": ["mzS1uMzO6hF1wlIoTg8d1g", ["Thai", "Noodles"]], "MMotl_bi3-5JRra91A2jLA": ["MMotl_bi3-5JRra91A2jLA", ["Malaysian", "Chinese", "Asian Fusion"]], "xyBTcpnkIxV2h0AKU0pP0Q": ["xyBTcpnkIxV2h0AKU0pP0Q", ["Vietnamese"]], "i6CpYdmMYoz712bRWTWVgQ": ["i6CpYdmMYoz712bRWTWVgQ", ["Asian Fusion", "Cocktail Bars"]], "YMcDo3UccCPvIJrQ5Yt9Yw": ["YMcDo3UccCPvIJrQ5Yt9Yw", ["Thai"]], "6CutdyyNi-wjh5QXMOielw": ["6CutdyyNi-wjh5QXMOielw", ["Thai", "Asian Fusion"]], "QWskQ2QpR8bmza2FRFziOQ": ["QWskQ2QpR8bmza2FRFziOQ", ["Asian Fusion", "Chinese", "Thai"]], "qn9dgCRGNjHKDGilBamkiw": ["qn9dgCRGNjHKDGilBamkiw", ["Thai", "Noodles"]], "HU7ILuZTmGZ6F_z6ZpHQfw": ["HU7ILuZTmGZ6F_z6ZpHQfw", ["Thai", "Asian Fusion", "Noodles"]], "PHu2RLIMZix9W4Uc-FS1fg": ["PHu2RLIMZix9W4Uc-FS1fg", ["Thai"]], "1Ed-tb_0dBGrXfsYyehmvg": ["1Ed-tb_0dBGrXfsYyehmvg", ["Asian Fusion", "Korean", "Singaporean"]], "VTNMeipIiyRRenXcRBedpg": ["VTNMeipIiyRRenXcRBedpg", ["Food Court", "Chinese", "Thai"]], "viB_c1ywQJJOr-zVQHkr0A": ["viB_c1ywQJJOr-zVQHkr0A", ["Thai"]], "vJ_lTYOkrZVSm0P042igBw": ["vJ_lTYOkrZVSm0P042igBw", ["Thai"]], "lDNiL1R3c0WMUI9jocJOzA": ["lDNiL1R3c0WMUI9jocJOzA", ["Sushi Bars", "Asian Fusion", "Thai"]], "u0qfikB-ppp6UwoNKqxlRw": ["u0qfikB-ppp6UwoNKqxlRw", ["Sushi Bars", "Japanese", "Asian Fusion"]], "Ci8ZAbhfNc0sj3kwj6XRmw": ["Ci8ZAbhfNc0sj3kwj6XRmw", ["Salad", "Vegan", "Gluten-Free"]], "LjBKkUSpMwrpo99hXgtHYw": ["LjBKkUSpMwrpo99hXgtHYw", ["Korean", "Vegan", "Asian Fusion"]], "fWX7sIzv_WTgZXdSwxYBPg": ["fWX7sIzv_WTgZXdSwxYBPg", ["Taiwanese", "Noodles", "Chinese"]], "CgsvKB65PZrZV8AhnD-wnw": ["CgsvKB65PZrZV8AhnD-wnw", ["Chinese", "Thai", "Seafood"]], "tYRWu_EDQGsIyhSaaYi7VQ": ["tYRWu_EDQGsIyhSaaYi7VQ", ["Vietnamese", "Sports Bars"]], "xvqG8x-EMcUysuOzY7RsPg": ["xvqG8x-EMcUysuOzY7RsPg", ["Thai", "Cocktail Bars"]], "RVv-A4ePzWoRoV4YToVATQ": ["RVv-A4ePzWoRoV4YToVATQ", ["Thai"]], "DNSFvZtdsqkaidmFSpm-Jw": ["DNSFvZtdsqkaidmFSpm-Jw", ["Noodles", "Izakaya"]], "IYRJ5E7fnK2UC0B5mOgzSQ": ["IYRJ5E7fnK2UC0B5mOgzSQ", ["Thai"]], "jOGL9SOeMH2F6HO5qxbDHw": ["jOGL9SOeMH2F6HO5qxbDHw", ["Thai"]], "9x7kLfuIYwvBDuFBUwd0yw": ["9x7kLfuIYwvBDuFBUwd0yw", ["Food Trucks", "Thai"]], "Up2LI3M1Uz3qJncRo0WgVw": ["Up2LI3M1Uz3qJncRo0WgVw", ["Vietnamese", "Sandwiches", "Asian Fusion"]], "kA_Cw1YEGskuPuRYzLmgdQ": ["kA_Cw1YEGskuPuRYzLmgdQ", ["Thai"]], "tEZTZG55c3TfeF-vbYOjog": ["tEZTZG55c3TfeF-vbYOjog", ["Thai"]], "yDR9eVFATpyzrz3x1DtJGg": ["yDR9eVFATpyzrz3x1DtJGg", ["Thai", "Food Trucks"]], "TwxP5xU_xyzlf7SVzCnpuA": ["TwxP5xU_xyzlf7SVzCnpuA", ["Noodles", "Ramen", "Vegan"]], "qd9_gxrmskbOT6OLN9sShA": ["qd9_gxrmskbOT6OLN9sShA", ["Ramen", "Thai", "Sushi Bars"]], "BeQgG_eup8mfs8qBDsRv6A": ["BeQgG_eup8mfs8qBDsRv6A", ["Sushi Bars", "Thai"]], "Il1K0hzGEiJgLLBCZCfA1A": ["Il1K0hzGEiJgLLBCZCfA1A", ["Thai", "Imported Food"]], "IXH26OJiL2hUSwNW_NJEhQ": ["IXH26OJiL2hUSwNW_NJEhQ", ["Food Trucks", "Thai"]], "QJ_tcL-PH5Cx1QYftTh3Ww": ["QJ_tcL-PH5Cx1QYftTh3Ww", ["Thai", "Chinese"]], "hSiTqxKKgvQSI5x5VdMjoQ": ["hSiTqxKKgvQSI5x5VdMjoQ", ["Thai"]], "OHLaE-7IMfMxEW6QhXND5Q": ["OHLaE-7IMfMxEW6QhXND5Q", ["Thai", "Barbeque"]], "BlBBmx4sLmoRW0tORiMDHQ": ["BlBBmx4sLmoRW0tORiMDHQ", ["Sushi Bars", "Japanese", "Thai"]], "UBnrFZuqa1nMrV7ncWHBwA": ["UBnrFZuqa1nMrV7ncWHBwA", ["Thai"]], "2UxAkvKkkWNwqZi9H0OzWw": ["2UxAkvKkkWNwqZi9H0OzWw", ["Chinese", "Noodles"]], "bRCNOrmz5S7q064UmIiZqw": ["bRCNOrmz5S7q064UmIiZqw", ["Asian Fusion", "Fast Food", "Thai"]], "BJT8aEHbK538gJ8Cx8AQVQ": ["BJT8aEHbK538gJ8Cx8AQVQ", ["Asian Fusion", "Sushi Bars", "Salad"]], "Wbmqg0TkOVkzNh3HrJ9DIQ": ["Wbmqg0TkOVkzNh3HrJ9DIQ", ["Vietnamese", "Sandwiches", "Soup"]], "0gMp5__7rq2csBndxnNtGQ": ["0gMp5__7rq2csBndxnNtGQ", ["Thai"]], "g6MkIQtn1XicZDJFPS6IQA": ["g6MkIQtn1XicZDJFPS6IQA", ["Thai"]], "q7U2GCMWIZxIqWeMDml0LQ": ["q7U2GCMWIZxIqWeMDml0LQ", ["Salad", "Vegan", "Vegetarian"]], "6QAE-LRmL3OEsHXGT9kuNw": ["6QAE-LRmL3OEsHXGT9kuNw", ["Noodles", "Szechuan"]], "mUl0wtO7tPkBocuJqZ-7Dw": ["mUl0wtO7tPkBocuJqZ-7Dw", ["Chinese", "Noodles"]], "pvxX-nvg3o-eZDlvrtYhQQ": ["pvxX-nvg3o-eZDlvrtYhQQ", ["Thai"]], "55jx0bYJ-odyqKKSrDXtPA": ["55jx0bYJ-odyqKKSrDXtPA", ["Japanese", "Asian Fusion"]], "dEp2ubj8SRGD32N3yw2h_A": ["dEp2ubj8SRGD32N3yw2h_A", ["Asian Fusion"]], "brMIenh-sAXr1zq6zpBKLA": ["brMIenh-sAXr1zq6zpBKLA", ["Thai"]], "RNrL9Z4m4ouGpOpPXpneRw": ["RNrL9Z4m4ouGpOpPXpneRw", ["Thai"]], "xG7W7SpI5_sJQXl-aIciIA": ["xG7W7SpI5_sJQXl-aIciIA", ["Thai"]], "pBNMZp_tKCAfRNx7-ybcHQ": ["pBNMZp_tKCAfRNx7-ybcHQ", ["Cuban", "Chinese", "Asian Fusion"]], "9c8M-3W7vuP4idvgi2LXSw": ["9c8M-3W7vuP4idvgi2LXSw", ["Thai", "Bubble Tea", "Comfort Food"]], "kVj4z8a4GUUmiJI0qLyVXg": ["kVj4z8a4GUUmiJI0qLyVXg", ["Malaysian", "Asian Fusion"]], "zqyGYIiCXL1Hz8KVZxbylQ": ["zqyGYIiCXL1Hz8KVZxbylQ", ["Vietnamese", "Sandwiches", "Noodles"]], "iB1tr_xJk7aAt0AhewoB9Q": ["iB1tr_xJk7aAt0AhewoB9Q", ["Thai"]], "DauDrnNt-P2Q0b1UMxA58A": ["DauDrnNt-P2Q0b1UMxA58A", ["Vietnamese"]], "WmweCnvSIPO8Nn-_PNeC7g": ["WmweCnvSIPO8Nn-_PNeC7g", ["Thai"]], "YvhVIOCXT8X71nkAy388Lg": ["YvhVIOCXT8X71nkAy388Lg", ["Thai"]], "MRzv1MW8M66vkHA8npV9lw": ["MRzv1MW8M66vkHA8npV9lw", ["Thai", "Vietnamese"]], "m4_k7yyNyU3yuUtb9CbpmQ": ["m4_k7yyNyU3yuUtb9CbpmQ", ["Thai"]], "Jxb84RRE0bduJnG4AddMkw": ["Jxb84RRE0bduJnG4AddMkw", ["Thai"]], "TBW3arqP85VbGqOlQ3PM1Q": ["TBW3arqP85VbGqOlQ3PM1Q", ["Chinese", "Sushi Bars", "Kosher"]], "_haIj6t4bGOmbIl3xtihpg": ["_haIj6t4bGOmbIl3xtihpg", ["Asian Fusion", "Fast Food"]], "-Q7D9350ODkZSz21td56gw": ["-Q7D9350ODkZSz21td56gw", ["Vietnamese", "Salad", "Soup"]], "zBf-m72ATTPTey-_9vu3Yw": ["zBf-m72ATTPTey-_9vu3Yw", ["Vegan", "Cafes"]], "gpt2U4ecZSCLmgVQPtkzbA": ["gpt2U4ecZSCLmgVQPtkzbA", ["Vietnamese", "Noodles", "Sandwiches"]], "PiOv4vMRLaJJoqt_Eyebvw": ["PiOv4vMRLaJJoqt_Eyebvw", ["Thai"]], "pb_cHcy8D8UC-jQ-Q524ug": ["pb_cHcy8D8UC-jQ-Q524ug", ["Asian Fusion", "Korean", "Chinese"]], "Z7gHAR1j_hjdxoWO7kYgeQ": ["Z7gHAR1j_hjdxoWO7kYgeQ", ["Japanese", "Sushi Bars", "Thai"]], "I6XC8dNxUzIcIOEbq3LJsQ": ["I6XC8dNxUzIcIOEbq3LJsQ", ["Chinese", "Seafood", "Thai"]], "f_OiLWqldSmNy1MAvtWlPQ": ["f_OiLWqldSmNy1MAvtWlPQ", ["Vietnamese", "Sandwiches", "Noodles"]], "dJYc9Hi0KJRMqCkCJOxC-w": ["dJYc9Hi0KJRMqCkCJOxC-w", ["Sushi Bars", "Japanese", "Thai"]], "0DyF6tokikZqd8bys-Af_Q": ["0DyF6tokikZqd8bys-Af_Q", ["Thai"]], "p2sAfaFyfFj9nYPyqcmQdw": ["p2sAfaFyfFj9nYPyqcmQdw", ["Street Vendors", "Thai"]], "ba-MPbYnM6T30RNgPdUvtQ": ["ba-MPbYnM6T30RNgPdUvtQ", ["Asian Fusion", "Cocktail Bars"]], "U74_3F7r3tMhd6dmTmDBxQ": ["U74_3F7r3tMhd6dmTmDBxQ", ["Asian Fusion", "Portuguese", "Chinese"]], "npiIhpcWePbVT3JYEcy3zg": ["npiIhpcWePbVT3JYEcy3zg", ["Indonesian", "French", "Venues & Event Spaces"]], "QJj-f8cpIs81NtlvS_Dc3w": ["QJj-f8cpIs81NtlvS_Dc3w", ["Thai", "Desserts", "Cafes"]], "T3KK5s1HaPGokXEc5Z8vOg": ["T3KK5s1HaPGokXEc5Z8vOg", ["Asian Fusion", "Thai", "Japanese"]], "jwKPVep2qZYBUA6SLLQPvg": ["jwKPVep2qZYBUA6SLLQPvg", ["Chinese", "Seafood", "Noodles"]], "l0zNwRbEQFP1pbbdXZZxcg": ["l0zNwRbEQFP1pbbdXZZxcg", ["Thai"]], "56rTisZA_iEekMsyZHvSHQ": ["56rTisZA_iEekMsyZHvSHQ", ["Sushi Bars", "Bubble Tea", "Noodles"]], "3LQD4aB3UYPteZfsyglV4w": ["3LQD4aB3UYPteZfsyglV4w", ["Japanese", "Thai", "Sushi Bars"]], "oUo_8ST8_fTKTEU6LYC65Q": ["oUo_8ST8_fTKTEU6LYC65Q", ["Japanese", "Asian Fusion", "Sushi Bars"]], "_du3ilTsbLqBmEY-ZyfqxA": ["_du3ilTsbLqBmEY-ZyfqxA", ["Vietnamese"]], "7Qvh0oFRsoqrO9qNlcMKXQ": ["7Qvh0oFRsoqrO9qNlcMKXQ", ["Sandwiches", "Coffee & Tea", "Salad"]], "IdZ5DnGnAEXcmz2jZXGFiQ": ["IdZ5DnGnAEXcmz2jZXGFiQ", ["Japanese", "Thai", "Sushi Bars"]], "8Oo2AtQEPDfxIOnA8wfXoQ": ["8Oo2AtQEPDfxIOnA8wfXoQ", ["Taiwanese", "Breakfast & Brunch", "Asian Fusion"]], "kqJApXkfFn42SZZG7QTc4w": ["kqJApXkfFn42SZZG7QTc4w", ["Vegan", "Asian Fusion", "Kosher"]], "YIYetgfNE34G8JhQu98XQw": ["YIYetgfNE34G8JhQu98XQw", ["Asian Fusion", "Sushi Bars"]], "2v7HpoqI2pSS9GpHu-gI2g": ["2v7HpoqI2pSS9GpHu-gI2g", ["Asian Fusion", "Bars"]], "b3XJAx3ru9FxB5gIxPZogg": ["b3XJAx3ru9FxB5gIxPZogg", ["Japanese", "Thai", "Sushi Bars"]], "Tk605KjXVTnXpGkOSuVBaQ": ["Tk605KjXVTnXpGkOSuVBaQ", ["Japanese", "Thai", "Chinese"]], "0DagPXrDResqZYEIqJSvgg": ["0DagPXrDResqZYEIqJSvgg", ["Food Trucks", "Vietnamese"]], "gNS0joGKALsNXFqKmZuurg": ["gNS0joGKALsNXFqKmZuurg", ["Chinese", "Thai"]], "SoBdWOxymmY5yKANn63UWw": ["SoBdWOxymmY5yKANn63UWw", ["Japanese", "Sushi Bars", "Asian Fusion"]], "xJlMHqnScLobt-Rr44Sotw": ["xJlMHqnScLobt-Rr44Sotw", ["Malaysian", "Thai"]], "lZiCOr0Ww28wElqq9DgrxA": ["lZiCOr0Ww28wElqq9DgrxA", ["Asian Fusion", "Filipino", "Thai"]], "1xJV03v3g3oP3G5oDlWuoQ": ["1xJV03v3g3oP3G5oDlWuoQ", ["Vietnamese", "Cocktail Bars"]], "3nWSUhGuLhEcUkWxO7LP8w": ["3nWSUhGuLhEcUkWxO7LP8w", ["Chinese", "Thai", "Asian Fusion"]], "Qacx-Vge9JcfkCPdkhle3Q": ["Qacx-Vge9JcfkCPdkhle3Q", ["Thai"]], "N0cfNApqwrPEqXgcf3NWmg": ["N0cfNApqwrPEqXgcf3NWmg", ["Chicken Wings", "Korean", "Asian Fusion"]], "BEuZGvNlbM4tXq7YICyM6w": ["BEuZGvNlbM4tXq7YICyM6w", ["Asian Fusion"]], "R8x9TlQ5zj-CzrjHVxHD-Q": ["R8x9TlQ5zj-CzrjHVxHD-Q", ["Caribbean", "Asian Fusion", "Breakfast & Brunch"]], "0AJ020rfdgxspffsdVNXxg": ["0AJ020rfdgxspffsdVNXxg", ["Thai"]], "wys1HhKwy80LSIRqG_prEg": ["wys1HhKwy80LSIRqG_prEg", ["Thai", "Cocktail Bars"]], "OuHB-EdeXmQ26QDzAsDxyw": ["OuHB-EdeXmQ26QDzAsDxyw", ["Food Trucks", "Thai"]], "fTpla27BQIfN5UWK6vjlQQ": ["fTpla27BQIfN5UWK6vjlQQ", ["Thai", "Chinese"]], "XB8hpls-B4ekyZvuouxqng": ["XB8hpls-B4ekyZvuouxqng", ["Japanese", "Asian Fusion"]], "xt8AcJzq61ksZbMJ1o--7Q": ["xt8AcJzq61ksZbMJ1o--7Q", ["Japanese", "Thai", "Sushi Bars"]], "3pFKz52MVF7dmIrKlUNBjw": ["3pFKz52MVF7dmIrKlUNBjw", ["Coffee & Tea", "Malaysian", "Thai"]], "UuiW2A-O11Q0baqSEUMvZA": ["UuiW2A-O11Q0baqSEUMvZA", ["Sushi Bars", "Japanese", "Thai"]], "uPVYeVOSLmvAkbxM9cTAQg": ["uPVYeVOSLmvAkbxM9cTAQg", ["Malaysian", "Chinese", "Cocktail Bars"]], "pF6DuOQMSXdZMrvzlrLdQg": ["pF6DuOQMSXdZMrvzlrLdQg", ["Vietnamese"]], "Swjm9no7DRqhThLlf0EHng": ["Swjm9no7DRqhThLlf0EHng", ["Cocktail Bars", "Pan Asian", "Tapas/Small Plates"]], "C3spvfEd8JQJie-yixRgpQ": ["C3spvfEd8JQJie-yixRgpQ", ["Vietnamese", "Desserts", "Coffee & Tea"]], "eQKYZWnBjPUjINAnFmrmbA": ["eQKYZWnBjPUjINAnFmrmbA", ["Chinese", "Asian Fusion", "Gluten-Free"]], "ev6e12vhY_0y4qE1cRhv0A": ["ev6e12vhY_0y4qE1cRhv0A", ["Noodles", "Izakaya"]], "1MqGlFP3b7H77fzUkJMKgw": ["1MqGlFP3b7H77fzUkJMKgw", ["Vietnamese", "Asian Fusion", "Sandwiches"]], "ynIx549QFj29o84y1RSGyw": ["ynIx549QFj29o84y1RSGyw", ["Cafes", "Asian Fusion", "Ramen"]], "uzSAWlBfrm-9xufAKbY9OA": ["uzSAWlBfrm-9xufAKbY9OA", ["Thai"]], "Gvg0ZLMsyZkLWHhT6uJs7w": ["Gvg0ZLMsyZkLWHhT6uJs7w", ["Thai", "Szechuan"]], "ldE6TJ4lo1OIg0eCig3ICg": ["ldE6TJ4lo1OIg0eCig3ICg", ["Vietnamese", "Sandwiches"]], "DY0y0KPwu8LnQteNB-uoAQ": ["DY0y0KPwu8LnQteNB-uoAQ", ["Lounges", "Asian Fusion", "Pubs"]], "3TaRBdVpHFIjKOEv_65qBw": ["3TaRBdVpHFIjKOEv_65qBw", ["Bubble Tea", "Malaysian", "Hot Pot"]], "8prcl4Adt88JLQVzL74xeQ": ["8prcl4Adt88JLQVzL74xeQ", ["Vietnamese"]], "-T_5QJwgPMxfXTeOmpImsA": ["-T_5QJwgPMxfXTeOmpImsA", ["Asian Fusion", "Beer Bar", "Izakaya"]], "HvN9eVtlm9MnOQCL_GlRSg": ["HvN9eVtlm9MnOQCL_GlRSg", ["Vietnamese"]], "Qi1AoRNcFEX8etII_RZkFg": ["Qi1AoRNcFEX8etII_RZkFg", ["Japanese", "Asian Fusion", "Sushi Bars"]], "pq7EMUOLCbQdKQ7PWL2bZA": ["pq7EMUOLCbQdKQ7PWL2bZA", ["Sandwiches", "Asian Fusion", "Cambodian"]], "FhXBKrLHyK7np4d0_f1s-w": ["FhXBKrLHyK7np4d0_f1s-w", ["Indian", "Chinese", "Thai"]], "gz8Pq_xgajTRf_5___82Cg": ["gz8Pq_xgajTRf_5___82Cg", ["Japanese", "Thai", "Sushi Bars"]], "iiZpFWVd1Cmd-cSOanmXAA": ["iiZpFWVd1Cmd-cSOanmXAA", ["Japanese", "Asian Fusion", "Sushi Bars"]], "s8W7-_v13OFJ-671FpL23w": ["s8W7-_v13OFJ-671FpL23w", ["Japanese", "Thai", "Sushi Bars"]], "IIKK1IKRVNEyE7lFo9pprQ": ["IIKK1IKRVNEyE7lFo9pprQ", ["Thai"]], "YCBjn0t4bMaQb8Bk7l37ng": ["YCBjn0t4bMaQb8Bk7l37ng", ["Chinese", "Kosher", "Thai"]], "NebgteFykeM1gwiVgPcCHw": ["NebgteFykeM1gwiVgPcCHw", ["Chinese", "Noodles"]], "OvdCm3j_5HzItolfvwrEUA": ["OvdCm3j_5HzItolfvwrEUA", ["Chinese", "Sushi Bars"]], "4MDltWx_2dxzTEv6mTRfSQ": ["4MDltWx_2dxzTEv6mTRfSQ", ["Burmese"]], "ov8JN2CZGk0fwDO3rtQYSg": ["ov8JN2CZGk0fwDO3rtQYSg", ["Thai"]], "3ik-lT8Pu7PAc_04af1J0w": ["3ik-lT8Pu7PAc_04af1J0w", ["Vegan"]], "QZgPeT9JGGvNgSr9i4m29Q": ["QZgPeT9JGGvNgSr9i4m29Q", ["Cuban", "Asian Fusion"]], "yiyc5wbgSCe13I7hj_jb-A": ["yiyc5wbgSCe13I7hj_jb-A", ["Vietnamese"]], "TzhAlljC_843JO7UDDUIaQ": ["TzhAlljC_843JO7UDDUIaQ", ["Chinese", "Noodles", "Taiwanese"]], "zj4vqgljRhxwWlvttgFRKQ": ["zj4vqgljRhxwWlvttgFRKQ", ["Asian Fusion", "Noodles"]], "iIcUpEOjMLuzAIfyY_vgYA": ["iIcUpEOjMLuzAIfyY_vgYA", ["Malaysian"]], "PBUIaPtgnhmdHE3KHglK-g": ["PBUIaPtgnhmdHE3KHglK-g", ["French", "American (New)", "Asian Fusion"]], "R8V6kbUtyfPAwNNu46vMvg": ["R8V6kbUtyfPAwNNu46vMvg", ["Noodles"]], "ROcLEpiaRRvKWrEn6hsulA": ["ROcLEpiaRRvKWrEn6hsulA", ["Asian Fusion", "Cuban", "Cocktail Bars"]], "CEEUDBFxvUPKGlA65qJ8JQ": ["CEEUDBFxvUPKGlA65qJ8JQ", ["Salad", "Vegan", "Gluten-Free"]], "Nmh-CXOo7fKWOCkPpc5ZpQ": ["Nmh-CXOo7fKWOCkPpc5ZpQ", ["Vietnamese"]], "AwiDxfV8j7x3_7dtUEkWmQ": ["AwiDxfV8j7x3_7dtUEkWmQ", ["Vietnamese", "Asian Fusion", "Noodles"]], "ZIxmqUDB_34TcTVSNusa6g": ["ZIxmqUDB_34TcTVSNusa6g", ["Thai"]], "7Q9qE3nxgJaUjrF8Iy_34Q": ["7Q9qE3nxgJaUjrF8Iy_34Q", ["Bars", "Vietnamese"]], "q2HGvziLlfQGChoDPFjTCQ": ["q2HGvziLlfQGChoDPFjTCQ", ["Indian", "Asian Fusion", "Thai"]], "iYFauSnqLxvr4HTY_cIElg": ["iYFauSnqLxvr4HTY_cIElg", ["Asian Fusion", "Vietnamese"]], "rN347NNwQ0hDSlbedzI9BQ": ["rN347NNwQ0hDSlbedzI9BQ", ["Asian Fusion", "Chinese", "Japanese"]], "fZuIszXbPoyzYMDSYd3oOA": ["fZuIszXbPoyzYMDSYd3oOA", ["Thai"]], "9ieA0TyApI94wEqqW_r93w": ["9ieA0TyApI94wEqqW_r93w", ["Chinese", "Thai"]], "GrxbGiLMkl1jd665k1lbIQ": ["GrxbGiLMkl1jd665k1lbIQ", ["Chinese", "Pan Asian"]], "Q_rT0lwuW8rJ6kGBYxPWkw": ["Q_rT0lwuW8rJ6kGBYxPWkw", ["Asian Fusion", "Japanese", "Sushi Bars"]], "PRQyJoum--REZ-yeEidyBg": ["PRQyJoum--REZ-yeEidyBg", ["Japanese", "Noodles"]], "BJn68qCExYQrPCT7CeOpzw": ["BJn68qCExYQrPCT7CeOpzw", ["Asian Fusion", "Vietnamese"]], "oe8GEFE4QLFAKt87y7zcgA": ["oe8GEFE4QLFAKt87y7zcgA", ["Taiwanese", "Chinese", "Noodles"]], "lt3Leywt1pzy23OzDqYRVA": ["lt3Leywt1pzy23OzDqYRVA", ["Chinese", "Thai", "Asian Fusion"]], "f1Q1n_dLzCvqU-dq0EBNsQ": ["f1Q1n_dLzCvqU-dq0EBNsQ", ["Vietnamese", "Malaysian", "Thai"]], "SVmsMnROrwlAN-c00QmoLg": ["SVmsMnROrwlAN-c00QmoLg", ["Asian Fusion"]], "Dqu-5RxNbbpBsL1Ssht9Ng": ["Dqu-5RxNbbpBsL1Ssht9Ng", ["Noodles", "Chinese"]], "B9_TgZa8rgW5oZOtXZUMCw": ["B9_TgZa8rgW5oZOtXZUMCw", ["Singaporean"]], "m_PhHkyN-630ucF7r2F8EQ": ["m_PhHkyN-630ucF7r2F8EQ", ["Vietnamese", "Soup", "Sandwiches"]], "h881bFbXCIZdI99-mPOoyA": ["h881bFbXCIZdI99-mPOoyA", ["Coffee & Tea", "Korean", "Asian Fusion"]], "owKe1hapqCCLnme2Xr3mrA": ["owKe1hapqCCLnme2Xr3mrA", ["Vietnamese", "Chinese"]], "2rjcqpDzCIHh1cyNFSh-4w": ["2rjcqpDzCIHh1cyNFSh-4w", ["Asian Fusion", "Chinese", "Burmese"]], "yH49flYj7qk9JOX124uhFg": ["yH49flYj7qk9JOX124uhFg", ["Vegan"]], "t1_qBEjXscQn-mp6-or_sw": ["t1_qBEjXscQn-mp6-or_sw", ["Asian Fusion", "Latin American", "Cocktail Bars"]], "qgMHSp9_5ppLB5nFE3KEYQ": ["qgMHSp9_5ppLB5nFE3KEYQ", ["Salad", "Grocery", "Vegetarian"]], "JylIStPfFLOctHdlglvALA": ["JylIStPfFLOctHdlglvALA", ["Coffee & Tea", "Breakfast & Brunch", "Vegan"]], "CMm3Xf-9v3QJ4ge20MoEVg": ["CMm3Xf-9v3QJ4ge20MoEVg", ["Vietnamese", "Sandwiches", "Noodles"]], "9GsphAby9n3-j_gP3k8KVA": ["9GsphAby9n3-j_gP3k8KVA", ["Thai"]], "WueXPnaTvM_R5UuPjxbbQw": ["WueXPnaTvM_R5UuPjxbbQw", ["Sushi Bars", "Asian Fusion", "Cocktail Bars"]], "YRuv0MBS7Fs5xZOW97J6IQ": ["YRuv0MBS7Fs5xZOW97J6IQ", ["Food Trucks", "Thai"]], "9FGJyUgdwLJHioLqz6tXfQ": ["9FGJyUgdwLJHioLqz6tXfQ", ["Cambodian", "Sandwiches"]], "ux6qiwZk--PBFFt2rdOChQ": ["ux6qiwZk--PBFFt2rdOChQ", ["Thai", "Food Trucks", "Noodles"]], "ves5zPXMxQk1-HK3E1fNhA": ["ves5zPXMxQk1-HK3E1fNhA", ["Pan Asian", "Japanese", "Cocktail Bars"]], "RYoc4EBUNOtgbg7c32OG9A": ["RYoc4EBUNOtgbg7c32OG9A", ["Korean", "Tapas/Small Plates", "Asian Fusion"]], "jIbFA311ECY4Fv4L0JikdQ": ["jIbFA311ECY4Fv4L0JikdQ", ["Vietnamese", "Soup"]], "3oB2_2vpeIyxJt1GvlcZBA": ["3oB2_2vpeIyxJt1GvlcZBA", ["Shanghainese", "Dim Sum", "Soup"]], "U2tjlMRITBSHHHTiv7L11A": ["U2tjlMRITBSHHHTiv7L11A", ["Japanese", "Sushi Bars", "Thai"]], "fBQvUemE3OVI1NAZt5KDFA": ["fBQvUemE3OVI1NAZt5KDFA", ["Vietnamese", "Pan Asian", "Soup"]], "iMaWDmb217ZJy2A025EQxA": ["iMaWDmb217ZJy2A025EQxA", ["Salad", "Soup", "Sandwiches"]], "3_R-YG5_KXS4m2ct5-QYhw": ["3_R-YG5_KXS4m2ct5-QYhw", ["Salad", "Vegan", "Gluten-Free"]], "C7e6WIM4CFa4EkzxHWHBRA": ["C7e6WIM4CFa4EkzxHWHBRA", ["Vietnamese"]], "dTyuWrk9KVtnHsWSY-ae-Q": ["dTyuWrk9KVtnHsWSY-ae-Q", ["Food Court", "Juice Bars & Smoothies", "Asian Fusion"]], "V2P3CWfUW_olSywlOlHGjQ": ["V2P3CWfUW_olSywlOlHGjQ", ["Asian Fusion", "Sushi Bars"]], "2ev7_7be5HVGfYJCEKEOgw": ["2ev7_7be5HVGfYJCEKEOgw", ["Sushi Bars", "Thai"]], "r6r-XK_wL02FQdAgaauTxg": ["r6r-XK_wL02FQdAgaauTxg", ["Ramen", "Noodles"]], "2rSmA4IK51QAQj60YGvjnw": ["2rSmA4IK51QAQj60YGvjnw", ["Asian Fusion", "Chinese"]], "w8mt6JTk8lUe7dTV6hASEw": ["w8mt6JTk8lUe7dTV6hASEw", ["Chinese", "Thai"]], "bZQryeTD6hIsT6lSUxzSSw": ["bZQryeTD6hIsT6lSUxzSSw", ["Vietnamese"]], "BKABojUN3G9vUrG3AlDZgQ": ["BKABojUN3G9vUrG3AlDZgQ", ["Asian Fusion", "Vegan"]], "cCqnycFCGIEiJJm3-A_BTg": ["cCqnycFCGIEiJJm3-A_BTg", ["Asian Fusion", "Sandwiches", "Korean"]], "VSfYR6MriVSQDAmO0gPFPQ": ["VSfYR6MriVSQDAmO0gPFPQ", ["Salad", "Vegetarian", "Grocery"]], "kxv4jD_qXRPVrV0oPR7isQ": ["kxv4jD_qXRPVrV0oPR7isQ", ["Szechuan", "Noodles"]], "VDbMrjBq-XAKZTS_cgB9_A": ["VDbMrjBq-XAKZTS_cgB9_A", ["Japanese", "Asian Fusion", "Chinese"]], "iueVEi_vQxdAzdXs-8Fvrg": ["iueVEi_vQxdAzdXs-8Fvrg", ["Japanese", "Sushi Bars", "Asian Fusion"]], "cWjl9L5VaM8lfUrb0dCPcg": ["cWjl9L5VaM8lfUrb0dCPcg", ["Vietnamese", "Bubble Tea"]], "DtkyPDGAodq5bAesiFa-JQ": ["DtkyPDGAodq5bAesiFa-JQ", ["Asian Fusion", "Sushi Bars", "Seafood"]], "JlFbaMbMzsu7FA307mUIqg": ["JlFbaMbMzsu7FA307mUIqg", ["Coffee & Tea", "Vietnamese", "Sandwiches"]], "1-o-uoVSaeUcorTYmHc6bw": ["1-o-uoVSaeUcorTYmHc6bw", ["Noodles", "Dim Sum", "Fast Food"]], "ePVlFbTzdVQFWie__kdplg": ["ePVlFbTzdVQFWie__kdplg", ["Chinese", "Noodles"]], "c9I4-T9wTlMmJEHb4obEdQ": ["c9I4-T9wTlMmJEHb4obEdQ", ["Chinese", "Thai"]], "XZswR1A0FMc3LZ-TmB8OYg": ["XZswR1A0FMc3LZ-TmB8OYg", ["Asian Fusion", "Malaysian"]], "n1EbqNtQQUg51rUd5A9_cA": ["n1EbqNtQQUg51rUd5A9_cA", ["Thai", "Noodles"]], "d96eV2MmIFi4zNNOxBdIZQ": ["d96eV2MmIFi4zNNOxBdIZQ", ["Chinese", "Asian Fusion"]], "r_auTWBu0-xW_9SQWLEdrg": ["r_auTWBu0-xW_9SQWLEdrg", ["Thai"]], "wctR1TrheHAwpHZ2sJknEw": ["wctR1TrheHAwpHZ2sJknEw", ["Middle Eastern", "Cafes", "Soup"]], "0jksmaH2Fiy3VTricU7g9A": ["0jksmaH2Fiy3VTricU7g9A", ["Chinese", "Japanese", "Thai"]], "NXZFu7KHBrG02gzYneY5Xg": ["NXZFu7KHBrG02gzYneY5Xg", ["Bars", "Asian Fusion", "Filipino"]], "vb-8neuGi8GPDTTnT2WO7g": ["vb-8neuGi8GPDTTnT2WO7g", ["Vietnamese"]], "sxwPYI-9XU3xgZcpqerDLQ": ["sxwPYI-9XU3xgZcpqerDLQ", ["Sushi Bars", "Japanese", "Thai"]], "PZlofInZTZnp2jwL3L5sqw": ["PZlofInZTZnp2jwL3L5sqw", ["Salad", "Sandwiches", "Soup"]], "1JShIY9vNv8fZ0VH9jR0tg": ["1JShIY9vNv8fZ0VH9jR0tg", ["Breakfast & Brunch", "Soup", "Cocktail Bars"]], "bzGe51q5j1AvKG7DbDZk5g": ["bzGe51q5j1AvKG7DbDZk5g", ["Thai", "Sushi Bars", "Asian Fusion"]], "Kjm5PwLywk7VICM6_tVRYQ": ["Kjm5PwLywk7VICM6_tVRYQ", ["Dim Sum", "Noodles", "Cantonese"]], "IQhHilj9mpMzjTFDmk_8aA": ["IQhHilj9mpMzjTFDmk_8aA", ["Singaporean", "Noodles", "Asian Fusion"]], "jyt3oRV7Ymp8XbMeD3UpBw": ["jyt3oRV7Ymp8XbMeD3UpBw", ["Vietnamese", "Soup", "Sandwiches"]], "B7bxdtvLYR7Nmex4AIFd4w": ["B7bxdtvLYR7Nmex4AIFd4w", ["Dim Sum", "Cantonese", "Asian Fusion"]], "mHBhUxHgDGjsB1LJl4qW0w": ["mHBhUxHgDGjsB1LJl4qW0w", ["Jazz & Blues", "American (New)", "Sushi Bars"]], "wQxJkDpO3kOSBRSsRi3CaA": ["wQxJkDpO3kOSBRSsRi3CaA", ["Asian Fusion", "Sushi Bars", "Japanese"]], "LpVbI-E9C-CSp7WhU5h2Iw": ["LpVbI-E9C-CSp7WhU5h2Iw", ["Seafood", "Chinese", "Asian Fusion"]], "ptWTdgSzSpH-0LD24QIH-w": ["ptWTdgSzSpH-0LD24QIH-w", ["Asian Fusion"]], "B6fXfY9Z-66OfISBD5-wuA": ["B6fXfY9Z-66OfISBD5-wuA", ["Thai"]], "yvg56iLnpb2cDb1rCZrCUA": ["yvg56iLnpb2cDb1rCZrCUA", ["Vietnamese"]], "ubX4CD4GqXpXjLfuBJo8HQ": ["ubX4CD4GqXpXjLfuBJo8HQ", ["Thai"]], "xWUL-j6TQyKQHIfOtetu-Q": ["xWUL-j6TQyKQHIfOtetu-Q", ["Vegetarian", "Korean", "Vegan"]], "KkMXFomcmJZBmDdmTMh8yw": ["KkMXFomcmJZBmDdmTMh8yw", ["Malaysian"]], "oFBgvlELwMtvqA0gcGr96g": ["oFBgvlELwMtvqA0gcGr96g", ["Asian Fusion", "Poke", "Sushi Bars"]], "CSJ-D61YYfWeweGzFMI0ww": ["CSJ-D61YYfWeweGzFMI0ww", ["Noodles", "Thai"]], "HDniG0HHT4d3ErVWTGLxZQ": ["HDniG0HHT4d3ErVWTGLxZQ", ["Sandwiches", "Salad", "Soup"]], "U-VF6WSAWTN_6iDpWd5kqw": ["U-VF6WSAWTN_6iDpWd5kqw", ["Vietnamese", "Sandwiches", "Coffee & Tea"]], "bGOZTD9O00OkVA1Pkt3OuQ": ["bGOZTD9O00OkVA1Pkt3OuQ", ["Chinese", "Asian Fusion", "Pan Asian"]], "Va_mnsEvBghHXvc7uZIWJQ": ["Va_mnsEvBghHXvc7uZIWJQ", ["Indian", "Chinese", "Salad"]], "v3BJ71AzK8tpSI8MpgNKFg": ["v3BJ71AzK8tpSI8MpgNKFg", ["Dim Sum", "Noodles", "Barbeque"]], "FsHqkVb0kmLq1VW7P-xz1A": ["FsHqkVb0kmLq1VW7P-xz1A", ["Asian Fusion", "Japanese", "Thai"]], "3n6i8TwGEIL9KnCCHUyiqA": ["3n6i8TwGEIL9KnCCHUyiqA", ["Asian Fusion", "Sushi Bars", "Japanese"]], "k4Aoi0jXt6S3W_lxCYO9Qg": ["k4Aoi0jXt6S3W_lxCYO9Qg", ["Chinese", "Thai"]], "bMhqh_k_QZJMnVstIJzxRw": ["bMhqh_k_QZJMnVstIJzxRw", ["Vietnamese"]], "Aw69I2eD-lYffytWGGYM8A": ["Aw69I2eD-lYffytWGGYM8A", ["Asian Fusion", "Tea Rooms"]], "5h-57YHVpnnl8fV_jMkQvg": ["5h-57YHVpnnl8fV_jMkQvg", ["Japanese", "Chinese", "Thai"]], "5AD9nY8UrYlCVMb3Y6KeWg": ["5AD9nY8UrYlCVMb3Y6KeWg", ["Korean", "Chicken Wings", "Asian Fusion"]], "TcuWyuZAORVnQBPCMNbTgw": ["TcuWyuZAORVnQBPCMNbTgw", ["Vegan", "Vegetarian", "Gluten-Free"]], "79-I5OTfhsfPCZGgcB4J5A": ["79-I5OTfhsfPCZGgcB4J5A", ["Sushi Bars", "Noodles", "Soup"]], "if1p9GpT78JbgcduQzzRYw": ["if1p9GpT78JbgcduQzzRYw", ["Asian Fusion", "Lounges", "Cocktail Bars"]], "1ht9x2hqzpjfk6JaR8r7oA": ["1ht9x2hqzpjfk6JaR8r7oA", ["Chinese", "Sushi Bars", "Asian Fusion"]], "LZ2Oq8xbDPc5HDfSk5J6jQ": ["LZ2Oq8xbDPc5HDfSk5J6jQ", ["Thai", "Pan Asian", "Japanese"]], "URflNuIV5PJZm4LcNACBPQ": ["URflNuIV5PJZm4LcNACBPQ", ["Music Venues", "Thai", "Beer, Wine & Spirits"]], "T_72OxeFKvdzX-mKEztHdQ": ["T_72OxeFKvdzX-mKEztHdQ", ["Asian Fusion", "Teppanyaki"]], "dH7jsvPhb6xhQkIu8Pv5jw": ["dH7jsvPhb6xhQkIu8Pv5jw", ["Bubble Tea", "Vietnamese", "Sandwiches"]], "7F9wHVknF_UW4OFVUDxtZQ": ["7F9wHVknF_UW4OFVUDxtZQ", ["Pan Asian"]], "7aRpGfetwrrnQ7hZgXQg8Q": ["7aRpGfetwrrnQ7hZgXQg8Q", ["Noodles"]], "kAwN-eXOLkZ4OJSRgmjojw": ["kAwN-eXOLkZ4OJSRgmjojw", ["Japanese", "Sushi Bars", "Thai"]], "ki9q3O-qk1YE-e2Uw1b5tA": ["ki9q3O-qk1YE-e2Uw1b5tA", ["Vietnamese"]], "98URsYAwTfXRPP5e1ONPug": ["98URsYAwTfXRPP5e1ONPug", ["Coffee & Tea", "International Grocery", "Asian Fusion"]], "uuDvk4EsRUkeTj4jVKJOpw": ["uuDvk4EsRUkeTj4jVKJOpw", ["French", "Sushi Bars", "Asian Fusion"]], "kzvcRu47MA2fPvW0WRPICA": ["kzvcRu47MA2fPvW0WRPICA", ["Thai"]], "0bDtHB75wr16A_8zUm_2ng": ["0bDtHB75wr16A_8zUm_2ng", ["Vegetarian"]], "WpfuHkTsiRN2EerQ8ZaG4g": ["WpfuHkTsiRN2EerQ8ZaG4g", ["Vietnamese", "Noodles", "Soup"]], "ai3pqIIsa0FdwCAzxb8dpg": ["ai3pqIIsa0FdwCAzxb8dpg", ["Thai"]], "vgQS_pLd4AftB4RNVnyD-A": ["vgQS_pLd4AftB4RNVnyD-A", ["Thai", "Chinese"]], "g5TxWia1evTKZAgr3T1Otg": ["g5TxWia1evTKZAgr3T1Otg", ["Japanese", "Thai", "Asian Fusion"]], "gcEMZjjqy5Ucnv_5Pv-q1g": ["gcEMZjjqy5Ucnv_5Pv-q1g", ["Noodles"]], "-HIsDolVluV6n5tlfQGB5w": ["-HIsDolVluV6n5tlfQGB5w", ["Asian Fusion", "Sushi Bars", "Ramen"]], "J9UA6rzI5WW_cDGjwDnF5g": ["J9UA6rzI5WW_cDGjwDnF5g", ["Japanese", "Noodles", "Soup"]], "mESab-FqL5QqSVsnX72asQ": ["mESab-FqL5QqSVsnX72asQ", ["Sushi Bars", "Ramen", "Salad"]], "poohyIxjSBu4p0WVRGaLrg": ["poohyIxjSBu4p0WVRGaLrg", ["Vietnamese", "Bubble Tea", "Sandwiches"]], "GXLGoW56JMm1lQf6Lnc15w": ["GXLGoW56JMm1lQf6Lnc15w", ["Thai", "Chinese"]], "KJFosOrLotvQo_rntg0sjA": ["KJFosOrLotvQo_rntg0sjA", ["Vietnamese", "Gastropubs", "Cocktail Bars"]], "nCQCd3iHbmGJzpbKk5cDhA": ["nCQCd3iHbmGJzpbKk5cDhA", ["Asian Fusion", "Ramen", "Cantonese"]], "4wfFugovobVrqSQ77ppjaQ": ["4wfFugovobVrqSQ77ppjaQ", ["Cocktail Bars", "Asian Fusion"]], "xEDD2ScBU3jHhWxlMC7dkQ": ["xEDD2ScBU3jHhWxlMC7dkQ", ["French", "Asian Fusion", "Breakfast & Brunch"]], "9DceMTrjyVqBgQRqgR6GWw": ["9DceMTrjyVqBgQRqgR6GWw", ["Vegetarian", "Soul Food", "Vegan"]], "cGSLzPA_SCWrN3cyT86Nhw": ["cGSLzPA_SCWrN3cyT86Nhw", ["Chinese", "Noodles"]], "kgX1iNxVYKFSQ9k0oPaeKA": ["kgX1iNxVYKFSQ9k0oPaeKA", ["Mediterranean", "Vegetarian", "Gluten-Free"]], "e9S-cBBVlNmnJGK8vBVyzg": ["e9S-cBBVlNmnJGK8vBVyzg", ["Soup"]], "JhJLPp6KuBcD3CHCkEKJ_A": ["JhJLPp6KuBcD3CHCkEKJ_A", ["Japanese", "Noodles", "Vegan"]], "pepM7-yv4-jCT6S1nl6fPg": ["pepM7-yv4-jCT6S1nl6fPg", ["Asian Fusion", "Malaysian", "Chinese"]], "REW3M3kvhl3ghw0hPQH5mQ": ["REW3M3kvhl3ghw0hPQH5mQ", ["Food Trucks", "Steakhouses", "Thai"]], "U73CjolqX-i0Wpa9AdPcmg": ["U73CjolqX-i0Wpa9AdPcmg", ["Food Trucks", "Noodles"]], "S-jThCG_S-7_xtm75nkB2Q": ["S-jThCG_S-7_xtm75nkB2Q", ["Malaysian", "Asian Fusion", "Cantonese"]], "sb1_MyLHzmjV1Jk21pyOIA": ["sb1_MyLHzmjV1Jk21pyOIA", ["Vietnamese", "Noodles", "Soup"]], "yDS7SUTAe6y3BYKdepIrbg": ["yDS7SUTAe6y3BYKdepIrbg", ["Asian Fusion", "Chinese", "Indian"]], "OZw7uy4wQyOUNF6gYC56sg": ["OZw7uy4wQyOUNF6gYC56sg", ["Sushi Bars", "Asian Fusion", "Chinese"]], "-KahGyU9G7JT0JmoC_Yc0Q": ["-KahGyU9G7JT0JmoC_Yc0Q", ["Cafes", "Asian Fusion", "Venues & Event Spaces"]], "M8eB6p4udxJhLkeIoDjBzA": ["M8eB6p4udxJhLkeIoDjBzA", ["Malaysian", "Taiwanese"]], "r1_1S1T6pSHK0imMjcr4hA": ["r1_1S1T6pSHK0imMjcr4hA", ["Asian Fusion", "Sushi Bars", "Salad"]], "GtfhGhWmr1kQ4EnFTlwg7w": ["GtfhGhWmr1kQ4EnFTlwg7w", ["Vegan", "Salad", "Gluten-Free"]], "j0n_poMVZnODYOFviLbh0Q": ["j0n_poMVZnODYOFviLbh0Q", ["Falafel", "Kosher", "Salad"]], "lQ8Fzgji9qmgRXkFcvAsVQ": ["lQ8Fzgji9qmgRXkFcvAsVQ", ["Chinese", "Noodles"]], "7QNfgCS66llLCsVu_8VOyA": ["7QNfgCS66llLCsVu_8VOyA", ["Vegan", "Vegetarian", "Juice Bars & Smoothies"]], "3DVKbi5cSLMlmph43RF_kA": ["3DVKbi5cSLMlmph43RF_kA", ["Asian Fusion", "Vegan"]], "7VqMGK9uwi0vKqOjdKyIUA": ["7VqMGK9uwi0vKqOjdKyIUA", ["Asian Fusion", "Sushi Bars", "Seafood"]], "1vjrqVCBMHyuGj4iX4TxsA": ["1vjrqVCBMHyuGj4iX4TxsA", ["Vegan", "American (New)"]], "klAhw3xLQi9GF1tf_HnS7w": ["klAhw3xLQi9GF1tf_HnS7w", ["Tapas Bars", "Sushi Bars", "Izakaya"]], "hq73x-YmjAh4KFsQdbQx7A": ["hq73x-YmjAh4KFsQdbQx7A", ["Thai"]], "01isnBO1rFO2LTOeNfYl9w": ["01isnBO1rFO2LTOeNfYl9w", ["American (New)", "Sushi Bars"]], "NUtJS2r8mPUk3kOJJQpEKw": ["NUtJS2r8mPUk3kOJJQpEKw", ["Chinese", "Thai"]], "boU8YGyv3xft7VwH37Bh2A": ["boU8YGyv3xft7VwH37Bh2A", ["Thai"]], "dJdIEYv56jTBkU6hAnSypw": ["dJdIEYv56jTBkU6hAnSypw", ["Asian Fusion", "Sushi Bars", "Indonesian"]], "NqnYnZtajJ4Y-Lmxa26VdA": ["NqnYnZtajJ4Y-Lmxa26VdA", ["Vietnamese", "Bubble Tea", "Coffee & Tea"]], "rFAbOFYXyV0gZxM7XIYRAQ": ["rFAbOFYXyV0gZxM7XIYRAQ", ["Asian Fusion", "Food Stands", "Sandwiches"]], "Xw34tTIGTE0WdWVmXc02Vw": ["Xw34tTIGTE0WdWVmXc02Vw", ["Vietnamese"]], "eBljpfHpo3m6oc5SFw-mLw": ["eBljpfHpo3m6oc5SFw-mLw", ["Vietnamese", "Wine Bars"]], "8cyRl5HIQzbkYD7orq223g": ["8cyRl5HIQzbkYD7orq223g", ["Asian Fusion", "Sushi Bars", "Japanese"]], "kNOr6_g6QfBHdhf89j3g5w": ["kNOr6_g6QfBHdhf89j3g5w", ["Taiwanese", "Chinese", "Noodles"]], "irRF-5aowSiEycwkKGw3Jw": ["irRF-5aowSiEycwkKGw3Jw", ["Vietnamese"]], "ZUJqeftWycx9uC1tS4pYZg": ["ZUJqeftWycx9uC1tS4pYZg", ["Salad", "Vegetarian"]], "cgiwHTmlUD-2em2MCvmzeA": ["cgiwHTmlUD-2em2MCvmzeA", ["Indonesian"]], "TMoFGaSlAlpEGjb9dOKPQg": ["TMoFGaSlAlpEGjb9dOKPQg", ["Salad", "Vegetarian"]], "ksqoC4U6u6HHyuWscFCzuQ": ["ksqoC4U6u6HHyuWscFCzuQ", ["Thai"]], "hqVvrxDVNKj36-ENaJCvZA": ["hqVvrxDVNKj36-ENaJCvZA", ["Salad", "Vegetarian"]], "Neiw4AB_s7BpLSxyUrSXBQ": ["Neiw4AB_s7BpLSxyUrSXBQ", ["Noodles", "Sushi Bars"]], "2VpurA2lb-q90nmALklNcA": ["2VpurA2lb-q90nmALklNcA", ["American (New)", "French", "Asian Fusion"]], "ONQRhDuWv0e9R5xOiI7YAA": ["ONQRhDuWv0e9R5xOiI7YAA", ["Japanese", "Barbeque", "Asian Fusion"]], "GGRMY-twaqZf_NIAprBJkg": ["GGRMY-twaqZf_NIAprBJkg", ["Chinese", "Noodles", "Salad"]], "jfoHx_QpcZcRP7TJAl0G7Q": ["jfoHx_QpcZcRP7TJAl0G7Q", ["Chinese", "Thai"]], "aMUu0H6jsUDqdmSuAZeZsg": ["aMUu0H6jsUDqdmSuAZeZsg", ["Ramen", "Sushi Bars", "Noodles"]], "8KWuqDFtoPEZGbTdfbX2ag": ["8KWuqDFtoPEZGbTdfbX2ag", ["Thai"]], "7xyLHOYIfoY6H5TOYwCuow": ["7xyLHOYIfoY6H5TOYwCuow", ["Vietnamese"]], "-6wpiKE7vCkFVb7GLCVcIw": ["-6wpiKE7vCkFVb7GLCVcIw", ["Thai", "Japanese", "Sushi Bars"]], "gdTLZb507By9ncborpZRMg": ["gdTLZb507By9ncborpZRMg", ["Szechuan", "Thai"]], "pqGGfA3Vm9srfTIJLgL0Ew": ["pqGGfA3Vm9srfTIJLgL0Ew", ["Cantonese", "Szechuan", "Noodles"]], "HOZsJkXLEWMy03TOMaH0jQ": ["HOZsJkXLEWMy03TOMaH0jQ", ["Vietnamese"]], "oizwTwvIitkCY_-czB8wqw": ["oizwTwvIitkCY_-czB8wqw", ["Chinese", "Japanese", "Thai"]], "Yv-_cU8CIJLUWXIMAjQPMQ": ["Yv-_cU8CIJLUWXIMAjQPMQ", ["Thai"]], "QGldR7s9_qV_35iGtkcNyA": ["QGldR7s9_qV_35iGtkcNyA", ["Chinese", "Asian Fusion", "Sushi Bars"]], "utItnelwAbkxF6GGHVopSg": ["utItnelwAbkxF6GGHVopSg", ["Vietnamese"]], "No4ny0agfERlycMQwkLD4w": ["No4ny0agfERlycMQwkLD4w", ["Filipino", "Asian Fusion", "Korean"]], "bYolHbAgMb-zOHpa41Lp0Q": ["bYolHbAgMb-zOHpa41Lp0Q", ["Vietnamese"]], "KXD44wWmrGf7mzyyr0bikw": ["KXD44wWmrGf7mzyyr0bikw", ["Vegetarian", "Bars", "Vegan"]], "BiFBVQwkCIurPP-ytstGwQ": ["BiFBVQwkCIurPP-ytstGwQ", ["Sushi Bars", "Japanese"]], "Vzx-7-jSEBz2g8NuGVhHvQ": ["Vzx-7-jSEBz2g8NuGVhHvQ", ["Chinese", "Asian Fusion"]], "tmPm9uEGh8q75Qe8bNTOgQ": ["tmPm9uEGh8q75Qe8bNTOgQ", ["Thai"]], "-n5zd4kpmJdqKzvar-5v8g": ["-n5zd4kpmJdqKzvar-5v8g", ["Korean", "Asian Fusion", "Fast Food"]], "D3LtTiVtIPOcUT_bjxztRA": ["D3LtTiVtIPOcUT_bjxztRA", ["Sushi Bars", "Teppanyaki", "Asian Fusion"]], "GURmB4kTMLpG8AGjx52ILw": ["GURmB4kTMLpG8AGjx52ILw", ["Asian Fusion"]], "S7ivv5O0beH3U9cV3cRD_Q": ["S7ivv5O0beH3U9cV3cRD_Q", ["Vegan", "Asian Fusion"]], "YtU1rb_oDHTbYzl-NFglPQ": ["YtU1rb_oDHTbYzl-NFglPQ", ["Burmese", "Food Stands"]], "j0Q-yyxS2WiL3foCJEV4eg": ["j0Q-yyxS2WiL3foCJEV4eg", ["Vegetarian", "Vegan"]], "bB3mkNsEkIpkwuaKSKxSfw": ["bB3mkNsEkIpkwuaKSKxSfw", ["Vegetarian", "Comfort Food", "Pan Asian"]], "3VZrUBCmSUt37jMB13-7yQ": ["3VZrUBCmSUt37jMB13-7yQ", ["Middle Eastern", "Mediterranean", "Vegetarian"]], "-Rat_jVuOv_HTYjHqooGzw": ["-Rat_jVuOv_HTYjHqooGzw", ["Malaysian", "Desserts", "Seafood"]], "3BYgbjo8MtaIyLZMdTxrOQ": ["3BYgbjo8MtaIyLZMdTxrOQ", ["Japanese", "Sushi Bars"]], "XZKNFGN10jzjEh7HIf0BDA": ["XZKNFGN10jzjEh7HIf0BDA", ["Thai", "Chinese"]], "Jn_p5WaprUY3Ql_539gsWw": ["Jn_p5WaprUY3Ql_539gsWw", ["Asian Fusion", "Sushi Bars"]], "ChOiuNbaglkVmrlk9lIIIA": ["ChOiuNbaglkVmrlk9lIIIA", ["Thai", "Chinese"]], "rPKXTHDgtGI4XEo2HuVpow": ["rPKXTHDgtGI4XEo2HuVpow", ["Australian", "Seafood", "Asian Fusion"]], "Xl0JBlbr-D4aICTMcYi5TA": ["Xl0JBlbr-D4aICTMcYi5TA", ["Noodles", "Chinese"]], "Jn7Wtek5_R12TKp2VUJuhw": ["Jn7Wtek5_R12TKp2VUJuhw", ["Noodles", "Chinese", "Taiwanese"]], "61JIVs4L3wmP1j4vJar1Tg": ["61JIVs4L3wmP1j4vJar1Tg", ["Cocktail Bars", "Asian Fusion", "Japanese"]], "oFzfFDDTVCqVBV9wHpZvNg": ["oFzfFDDTVCqVBV9wHpZvNg", ["Thai"]], "i9ohlvanaW3c9o5_6ziXDw": ["i9ohlvanaW3c9o5_6ziXDw", ["Salad", "Soup", "Sandwiches"]], "wfhMIiMh2A2psCGONOVSlg": ["wfhMIiMh2A2psCGONOVSlg", ["Szechuan", "Noodles", "Beer Bar"]], "EvLkJaWEXTZ8QNBrxOhDsA": ["EvLkJaWEXTZ8QNBrxOhDsA", ["Vietnamese"]], "5rX_7IkvFx5MKqS3ikQe3Q": ["5rX_7IkvFx5MKqS3ikQe3Q", ["Chinese", "Thai"]], "-i0Gr_1jpubMff55GBxe0Q": ["-i0Gr_1jpubMff55GBxe0Q", ["Seafood", "Thai"]], "8cFOJd4dTkkE7EFUns8kGQ": ["8cFOJd4dTkkE7EFUns8kGQ", ["Asian Fusion", "Japanese", "Sushi Bars"]], "dL6_XUUr_INX10IOMtSM0w": ["dL6_XUUr_INX10IOMtSM0w", ["Japanese", "Sushi Bars"]], "dDXtga5Kgo5B1twdezcZJA": ["dDXtga5Kgo5B1twdezcZJA", ["Chinese", "Asian Fusion"]], "1dV_a1iskf_S4J-vc5hW3w": ["1dV_a1iskf_S4J-vc5hW3w", ["Vietnamese", "Soup"]], "VGOSQXDBT1pHhqAB7_B8mA": ["VGOSQXDBT1pHhqAB7_B8mA", ["Japanese", "Sushi Bars", "Thai"]], "tFFLetrWW6-7KW74eryspQ": ["tFFLetrWW6-7KW74eryspQ", ["Sushi Bars", "Japanese", "Seafood"]], "MDMw0HFK3rgeGRl-FZC9Fg": ["MDMw0HFK3rgeGRl-FZC9Fg", ["Vietnamese", "Sandwiches"]], "gNMT6UQ7gKMfMK96jbRDDw": ["gNMT6UQ7gKMfMK96jbRDDw", ["Salad", "Vegetarian", "Grocery"]], "XoJwcOxazBKvWikQCATS-w": ["XoJwcOxazBKvWikQCATS-w", ["Breakfast & Brunch", "Noodles", "Dim Sum"]], "4UqmQ-zLrbICQFoDhr5XnQ": ["4UqmQ-zLrbICQFoDhr5XnQ", ["Sushi Bars", "Salad", "Soup"]], "lxQ-tzFmL1tmUqZUN-CSRQ": ["lxQ-tzFmL1tmUqZUN-CSRQ", ["Japanese", "Asian Fusion"]], "I_Va7AZSHpEwX75S-3hHLQ": ["I_Va7AZSHpEwX75S-3hHLQ", ["Chinese", "Noodles"]], "qy7CaBk9g519-iZGjrki1g": ["qy7CaBk9g519-iZGjrki1g", ["Vietnamese"]], "zD0BvDF_E3POMJ1BXyQbDQ": ["zD0BvDF_E3POMJ1BXyQbDQ", ["Filipino", "Asian Fusion", "Desserts"]], "q23Br0CDFO6a1qx_7ItFKA": ["q23Br0CDFO6a1qx_7ItFKA", ["Sushi Bars", "Noodles", "Ramen"]], "2YkqGzOldh-gcSSFkvP44Q": ["2YkqGzOldh-gcSSFkvP44Q", ["Asian Fusion", "Poke", "Acai Bowls"]], "VIur-OanRPkNvbo9rXRlEQ": ["VIur-OanRPkNvbo9rXRlEQ", ["Dim Sum", "Pan Asian"]], "R9fhVXmtgRwZNgOr-kNWHA": ["R9fhVXmtgRwZNgOr-kNWHA", ["Breakfast & Brunch", "Cafes", "Asian Fusion"]], "D9g4zcLw26jMaDrBwzpdCA": ["D9g4zcLw26jMaDrBwzpdCA", ["Vietnamese", "Sandwiches", "Soup"]], "Xmel8w9le4GEtidgYWu8Vw": ["Xmel8w9le4GEtidgYWu8Vw", ["Soup"]], "-TtI1Y6k4Tz4oECabs6mcA": ["-TtI1Y6k4Tz4oECabs6mcA", ["Food Court", "Asian Fusion", "Chinese"]], "WlhkVLite9TQrtnzYLiO4Q": ["WlhkVLite9TQrtnzYLiO4Q", ["Vietnamese", "Noodles", "Sandwiches"]], "3Pj_6JogAypgXNhM1-iSPQ": ["3Pj_6JogAypgXNhM1-iSPQ", ["Vegan", "Asian Fusion", "Venues & Event Spaces"]], "tVE5TyJ4NYj_Vw_6mFyRig": ["tVE5TyJ4NYj_Vw_6mFyRig", ["Soup", "Sandwiches", "Salad"]], "d8zSYpArh4oXpxeJWNA4Pg": ["d8zSYpArh4oXpxeJWNA4Pg", ["Vegetarian", "Moroccan", "Greek"]], "wr6k2PrOKPc7UC2S4izxjg": ["wr6k2PrOKPc7UC2S4izxjg", ["Asian Fusion", "Soup", "Thai"]], "IoPJ1I0eQn6wnrFAoqFXOw": ["IoPJ1I0eQn6wnrFAoqFXOw", ["Vietnamese", "Bubble Tea", "Sandwiches"]], "1gK-0_lGqjxbwiHWcXXdzg": ["1gK-0_lGqjxbwiHWcXXdzg", ["American (New)", "Bars", "Vegan"]], "anayUOcPkiAvijszwOf_Rw": ["anayUOcPkiAvijszwOf_Rw", ["Vegan", "Comfort Food"]], "WV4wZZVIKmanuAEpHo-rZA": ["WV4wZZVIKmanuAEpHo-rZA", ["Delis", "Vegetarian", "Juice Bars & Smoothies"]], "JnjBLhhFpbWrKuN81KUPtg": ["JnjBLhhFpbWrKuN81KUPtg", ["Salad", "Vegetarian"]], "Bb0h5Rs8ugSM2CjulRhfBw": ["Bb0h5Rs8ugSM2CjulRhfBw", ["Szechuan", "Vegan"]], "FOQTQd_kosGcwetdsZjEiA": ["FOQTQd_kosGcwetdsZjEiA", ["Salad", "Vegan", "Gluten-Free"]], "aeZOg5kehkVOoLBCFEqsxQ": ["aeZOg5kehkVOoLBCFEqsxQ", ["Asian Fusion"]], "3m9zzglPW2M1bPikC3XpRg": ["3m9zzglPW2M1bPikC3XpRg", ["Vietnamese"]], "D9nQb14gqhCAOaUUvJz3-Q": ["D9nQb14gqhCAOaUUvJz3-Q", ["Steakhouses", "Kosher", "Asian Fusion"]], "mmQuBKL2Q3HCBqQrR7FmQA": ["mmQuBKL2Q3HCBqQrR7FmQA", ["Asian Fusion"]], "Zx44jCgDv1TwKMGzcXajIQ": ["Zx44jCgDv1TwKMGzcXajIQ", ["Malaysian"]], "qHD05vCitNTTPMyvU2Sh7g": ["qHD05vCitNTTPMyvU2Sh7g", ["Asian Fusion", "Chinese", "Tapas/Small Plates"]], "rw5uKUdVo2slHHEtKTBDgg": ["rw5uKUdVo2slHHEtKTBDgg", ["Asian Fusion", "Bubble Tea", "Gluten-Free"]], "Z5JY0Wq4dctTdlFQxPVECg": ["Z5JY0Wq4dctTdlFQxPVECg", ["Asian Fusion", "Kosher", "Vegan"]], "A0saPXtRGKl-SVJGQyQAOw": ["A0saPXtRGKl-SVJGQyQAOw", ["Dim Sum", "Steakhouses", "Asian Fusion"]], "1cH4vC7OOtAd1GrQ0FcY5Q": ["1cH4vC7OOtAd1GrQ0FcY5Q", ["Vegetarian", "Salad"]], "VEjkxniAlG35cR3pjHvF-A": ["VEjkxniAlG35cR3pjHvF-A", ["Chinese", "Halal", "Asian Fusion"]], "SwJ6HEFHwIwH4HekceoyCA": ["SwJ6HEFHwIwH4HekceoyCA", ["Sandwiches", "Salad", "Soup"]], "Be5anr2hGPZg8tJhbDl6fw": ["Be5anr2hGPZg8tJhbDl6fw", ["Food Delivery Services"]], "CqQ2Og9kf-LhlUWtODalCQ": ["CqQ2Og9kf-LhlUWtODalCQ", ["Sushi Bars", "Japanese", "Cocktail Bars"]], "TemMTqYoDJ53doNF-PCKZA": ["TemMTqYoDJ53doNF-PCKZA", ["Halal", "Uzbek", "Asian Fusion"]], "U358IKiKV5uGjhR_H2NjVQ": ["U358IKiKV5uGjhR_H2NjVQ", ["Thai", "Chinese"]], "3RuiiqUg8C3HZ-RuvlqtBg": ["3RuiiqUg8C3HZ-RuvlqtBg", ["Indian", "Chinese", "Thai"]], "85y2x_yaBAEGDtwkhqe6ug": ["85y2x_yaBAEGDtwkhqe6ug", ["Japanese", "Thai", "Chinese"]], "ymO4zdB_EOJzlojJRbnm8A": ["ymO4zdB_EOJzlojJRbnm8A", ["Salad", "Bubble Tea", "Asian Fusion"]], "GeXd_6XseU9E8oC1p1SaNg": ["GeXd_6XseU9E8oC1p1SaNg", ["Salad", "Vegetarian"]], "D9uG__LwKnsRT5jA6L1Wtg": ["D9uG__LwKnsRT5jA6L1Wtg", ["Salad", "Vegan", "Juice Bars & Smoothies"]], "RABCwRzA1YCSpIWuk9LgqA": ["RABCwRzA1YCSpIWuk9LgqA", ["Soul Food", "Vegan", "Comfort Food"]], "SSDOkx5enfRH3nsniS_2jA": ["SSDOkx5enfRH3nsniS_2jA", ["Vietnamese", "Coffee & Tea", "Salad"]], "lWiGt3bH7k2Zxynh9hE92g": ["lWiGt3bH7k2Zxynh9hE92g", ["Salad", "Sandwiches", "Soup"]], "4hukJNoy9F2ILYJZWl4Xlw": ["4hukJNoy9F2ILYJZWl4Xlw", ["Gastropubs", "Asian Fusion", "American (New)"]], "4x5suSKSAOKYdTvKaRKxKQ": ["4x5suSKSAOKYdTvKaRKxKQ", ["Vietnamese", "Seafood", "Soup"]], "_2V0as8DZDwVxAi3ZJ0JkA": ["_2V0as8DZDwVxAi3ZJ0JkA", ["Japanese", "Sushi Bars"]], "8AM1gGIk6KVb27Q9TYwD9Q": ["8AM1gGIk6KVb27Q9TYwD9Q", ["Vegetarian", "Salad", "Juice Bars & Smoothies"]], "gymgQ5S_83IxaAtH0cJMsA": ["gymgQ5S_83IxaAtH0cJMsA", ["Salad", "Vegetarian", "Grocery"]], "6salH2D1m9Fe_SMH1tTscQ": ["6salH2D1m9Fe_SMH1tTscQ", ["Salad", "Vegetarian", "Grocery"]], "Dj0jblwuWTftL1D7_Kun6Q": ["Dj0jblwuWTftL1D7_Kun6Q", ["Chinese", "Noodles", "Vietnamese"]], "4xOPFgrVjxKmRPlfKH-Meg": ["4xOPFgrVjxKmRPlfKH-Meg", ["Vietnamese"]], "AaGq5Peah3Z-2TUBMtlC2Q": ["AaGq5Peah3Z-2TUBMtlC2Q", ["Noodles", "Taiwanese", "Chinese"]], "VFm8KI_no47AOHUDYYGTVA": ["VFm8KI_no47AOHUDYYGTVA", ["Asian Fusion", "Breakfast & Brunch"]], "nrxSzq-VxLqD7aFkE4SH3Q": ["nrxSzq-VxLqD7aFkE4SH3Q", ["Japanese", "Noodles", "Soup"]], "HScFap2SwbUlfC-QXVkxFA": ["HScFap2SwbUlfC-QXVkxFA", ["Chinese", "Burgers", "Noodles"]], "hg9XXLb2AeJHJ7eX-6JnMg": ["hg9XXLb2AeJHJ7eX-6JnMg", ["Vietnamese", "Chicken Shop"]], "ooHTw6KGNXsKj5TmyHKVuQ": ["ooHTw6KGNXsKj5TmyHKVuQ", ["Vietnamese", "Sandwiches", "Noodles"]], "FCvWw_e__UfxYusrC99Klw": ["FCvWw_e__UfxYusrC99Klw", ["Vietnamese"]], "tguMh2GgOcU9fu6WN3dqpw": ["tguMh2GgOcU9fu6WN3dqpw", ["Chinese", "Kosher", "Vegan"]], "72ldgXvlHB9xzyLsgMGCQA": ["72ldgXvlHB9xzyLsgMGCQA", ["Sushi Bars"]], "aIPbIdP2l9cWxVdtIRwYrA": ["aIPbIdP2l9cWxVdtIRwYrA", ["Sushi Bars", "Asian Fusion"]], "GzY2EjCmGNgvRd7IE20fTA": ["GzY2EjCmGNgvRd7IE20fTA", ["Asian Fusion", "Japanese", "Chinese"]], "jLhKLKuNPMTzAMJgEY5DsQ": ["jLhKLKuNPMTzAMJgEY5DsQ", ["Pan Asian", "Cocktail Bars"]], "hUf1EpnxbxFU4gf2nL7H-Q": ["hUf1EpnxbxFU4gf2nL7H-Q", ["Sushi Bars", "Ramen"]], "79xCcUlhPtZ5tZFlTRDUsQ": ["79xCcUlhPtZ5tZFlTRDUsQ", ["American (New)", "Vegetarian", "Bars"]], "3Hq79elupsM-npDRxCo1tA": ["3Hq79elupsM-npDRxCo1tA", ["Salad", "Vegetarian"]], "bB8dHfAEJrF5tNcHr0yJjA": ["bB8dHfAEJrF5tNcHr0yJjA", ["Japanese", "Barbeque", "Asian Fusion"]], "qCskreGDQeNj5927Y2xEZQ": ["qCskreGDQeNj5927Y2xEZQ", ["Asian Fusion", "Chinese", "Sushi Bars"]], "awzOmL5ykp7q4qTh1n7kmQ": ["awzOmL5ykp7q4qTh1n7kmQ", ["Vietnamese"]], "-edCxB-9khQrBsqXNcBg1A": ["-edCxB-9khQrBsqXNcBg1A", ["Japanese", "Chinese", "Thai"]], "Ypz7j5vm0kZ2XqpjGjbHNw": ["Ypz7j5vm0kZ2XqpjGjbHNw", ["Malaysian", "Desserts", "Chinese"]], "U8PkzJYfq3YpCx52ciNv3w": ["U8PkzJYfq3YpCx52ciNv3w", ["Vietnamese"]], "RLAs8M-IQfAgp551rkFNGg": ["RLAs8M-IQfAgp551rkFNGg", ["Japanese", "Chinese", "Sushi Bars"]], "a_gZcWqimP6iTMM49MeYAQ": ["a_gZcWqimP6iTMM49MeYAQ", ["Vietnamese"]], "Hqczhc7MtIy_bzxhOpaXLg": ["Hqczhc7MtIy_bzxhOpaXLg", ["Salad", "Vegetarian", "Grocery"]], "G4qZvheX74VwYvek7I8iQg": ["G4qZvheX74VwYvek7I8iQg", ["Asian Fusion", "Ramen", "Sushi Bars"]], "Upy5v6_311t1CUV3ru4jQA": ["Upy5v6_311t1CUV3ru4jQA", ["Chinese", "Thai"]], "NVcKEwdKGSSDnIAceebMpw": ["NVcKEwdKGSSDnIAceebMpw", ["Asian Fusion"]], "O4fJTI3e11PsKwIOYGZkag": ["O4fJTI3e11PsKwIOYGZkag", ["Salad", "Vegetarian"]], "7hh2eP4HVkyjtpcqeITk3Q": ["7hh2eP4HVkyjtpcqeITk3Q", ["Cantonese", "Noodles", "Szechuan"]], "D65eObUbArHu6UiQsUasgw": ["D65eObUbArHu6UiQsUasgw", ["Ramen", "Soup"]], "2dkrCgx3h8hPRdkoj0QJjw": ["2dkrCgx3h8hPRdkoj0QJjw", ["Soup", "Gluten-Free"]], "lGLeaVcg7U4tOfJFhVqGng": ["lGLeaVcg7U4tOfJFhVqGng", ["Indonesian", "Noodles", "Soup"]], "OPZdWfI1DyLZTLPeDM91pQ": ["OPZdWfI1DyLZTLPeDM91pQ", ["Hawaiian", "Asian Fusion", "Poke"]], "qFZuYdXy57_ydnsEFdfOxA": ["qFZuYdXy57_ydnsEFdfOxA", ["Hot Pot", "Seafood", "Noodles"]], "sY5j4zQuWRGxHG6T7EunrQ": ["sY5j4zQuWRGxHG6T7EunrQ", ["Pizza", "Vegan", "Gluten-Free"]], "NZ0zBJ60QNrol6nUeAnLgw": ["NZ0zBJ60QNrol6nUeAnLgw", ["Vietnamese", "Sandwiches", "Bubble Tea"]], "zoJRxiyaLGV1BitvduDFcw": ["zoJRxiyaLGV1BitvduDFcw", ["Salad", "Vegetarian"]], "LZA0bWz_Xn--tSgiaPLlkw": ["LZA0bWz_Xn--tSgiaPLlkw", ["Salad", "Vegetarian"]], "ocXYGC2oiGDJSzA7qu4SGw": ["ocXYGC2oiGDJSzA7qu4SGw", ["Sandwiches", "Vietnamese"]], "HkTeodZ690Lkukhui4INlA": ["HkTeodZ690Lkukhui4INlA", ["Vietnamese", "Coffee & Tea", "Sandwiches"]], "sKIYGvENchifk1YwFe77pA": ["sKIYGvENchifk1YwFe77pA", ["Vietnamese"]], "WMpuPDhPXsbRdhTzGIhaQw": ["WMpuPDhPXsbRdhTzGIhaQw", ["Vietnamese"]], "XD9XiCUvbvCt7laocvAadw": ["XD9XiCUvbvCt7laocvAadw", ["Sushi Bars", "Asian Fusion", "Cocktail Bars"]], "QKXtUgCauU98U5zNJV8vuA": ["QKXtUgCauU98U5zNJV8vuA", ["Gastropubs", "Sandwiches", "Vegan"]], "xscOfj1dMkEKvhrRruLpIg": ["xscOfj1dMkEKvhrRruLpIg", ["Vegetarian", "Seafood"]], "h4KVbPYmLPticRz3iIzM-w": ["h4KVbPYmLPticRz3iIzM-w", ["Vietnamese"]], "_pXppRVEAW6zi8uRjx1ULg": ["_pXppRVEAW6zi8uRjx1ULg", ["Salad", "Breakfast & Brunch", "American (Traditional)"]], "U2rFQLQ9zO9TMSkM5eNMcg": ["U2rFQLQ9zO9TMSkM5eNMcg", ["Sandwiches", "Soup", "Salad"]], "pe0kLJDb7DEWSKCbOS8D2g": ["pe0kLJDb7DEWSKCbOS8D2g", ["Japanese", "Sushi Bars", "Sports Bars"]], "diOj0F4AZuiqzNTu-z3hOQ": ["diOj0F4AZuiqzNTu-z3hOQ", ["Vietnamese", "Bubble Tea", "Sandwiches"]], "ZLZswviJ0CSX5ZeQFSO2sQ": ["ZLZswviJ0CSX5ZeQFSO2sQ", ["Vietnamese"]], "L_-RylYupDJG1leOCXQwcQ": ["L_-RylYupDJG1leOCXQwcQ", ["Thai"]], "7R0MMcPaxUyeUqjCwLyOCQ": ["7R0MMcPaxUyeUqjCwLyOCQ", ["Vegan"]], "2CMgTjJoC3II30mxRy-G8A": ["2CMgTjJoC3II30mxRy-G8A", ["Sushi Bars", "Japanese", "Asian Fusion"]], "fPPlnbcVExevivoNEgnS7A": ["fPPlnbcVExevivoNEgnS7A", ["Sandwiches", "Salad", "Soup"]], "zhkyBId_RIPyiOFE2R1PRg": ["zhkyBId_RIPyiOFE2R1PRg", ["Sushi Bars", "Japanese", "Asian Fusion"]], "0vg2Z-HPwkyVVX613j2ysg": ["0vg2Z-HPwkyVVX613j2ysg", ["Chinese", "Noodles", "Ramen"]], "eJW43S76Sy2wwA3VeZzKkQ": ["eJW43S76Sy2wwA3VeZzKkQ", ["Salad", "Vegetarian"]], "M0BQ0_tPbrwsiwKELIL1fw": ["M0BQ0_tPbrwsiwKELIL1fw", ["Sushi Bars", "Chinese", "Asian Fusion"]], "kFV-XAalWCEZN5VW77_3Hg": ["kFV-XAalWCEZN5VW77_3Hg", ["Sandwiches", "Fruits & Veggies", "Vegetarian"]], "sDgN-TGeEz-wd8kWEUWwTA": ["sDgN-TGeEz-wd8kWEUWwTA", ["Vegan", "Latin American"]], "ubCFsHLAG_xZupEbCny7vA": ["ubCFsHLAG_xZupEbCny7vA", ["Ramen", "Noodles", "Beer Bar"]], "RjblkxUBTtzG-tcgFyCofA": ["RjblkxUBTtzG-tcgFyCofA", ["Mexican", "Seafood", "Asian Fusion"]], "t7BIiUN0tFg33kySuuQ0aQ": ["t7BIiUN0tFg33kySuuQ0aQ", ["Sushi Bars", "Japanese"]], "HaRZCA7LK8BzG0buH2SaZA": ["HaRZCA7LK8BzG0buH2SaZA", ["Desserts", "Ice Cream & Frozen Yogurt", "Food Delivery Services"]], "S1yH5vdJh2L2UIb7zJ2OHg": ["S1yH5vdJh2L2UIb7zJ2OHg", ["Japanese", "Sushi Bars", "Asian Fusion"]], "EGUPGM2TuwMMFi3vifYEVA": ["EGUPGM2TuwMMFi3vifYEVA", ["Vegetarian", "Asian Fusion", "Vegan"]], "S0Qydvh12n5E_uodsLa8eA": ["S0Qydvh12n5E_uodsLa8eA", ["Juice Bars & Smoothies", "Asian Fusion", "Vegan"]], "69_uRnB0amB6FbmASCo0-A": ["69_uRnB0amB6FbmASCo0-A", ["Vietnamese", "Korean"]], "BY-oHxO410rDVhX0yRAvQQ": ["BY-oHxO410rDVhX0yRAvQQ", ["Thai", "Chinese"]], "cAu-1t90dUdcSDI5ZvYqEg": ["cAu-1t90dUdcSDI5ZvYqEg", ["Sushi Bars", "Thai", "Asian Fusion"]], "xR2Yeb_Nh0MOAiUIaqaVOg": ["xR2Yeb_Nh0MOAiUIaqaVOg", ["Wine Bars", "Asian Fusion", "Tapas/Small Plates"]], "X9uu1kPZYlKJfI1baiJBPQ": ["X9uu1kPZYlKJfI1baiJBPQ", ["Chinese", "Noodles"]], "FiVvY9ya4tbU5o2l9FZ0KA": ["FiVvY9ya4tbU5o2l9FZ0KA", ["Soup"]], "vZgJyMZlpSSS_Y-duxd4_A": ["vZgJyMZlpSSS_Y-duxd4_A", ["Dim Sum", "Noodles", "Szechuan"]], "74SKT4IxG-hXz71nRbheng": ["74SKT4IxG-hXz71nRbheng", ["Asian Fusion", "Bars"]], "dOxHYQmBR14Fa2C1X8oMMQ": ["dOxHYQmBR14Fa2C1X8oMMQ", ["Sushi Bars", "Japanese"]], "_WXa2M3gz2Mi0ys3s88nDw": ["_WXa2M3gz2Mi0ys3s88nDw", ["Asian Fusion", "Chinese"]], "Ew3d7Vt18c1MH4_X6ogxQQ": ["Ew3d7Vt18c1MH4_X6ogxQQ", ["Vietnamese", "Sandwiches", "Salad"]], "7wJTUI8NmBNmZoN4zrXCPw": ["7wJTUI8NmBNmZoN4zrXCPw", ["Asian Fusion"]], "R0y03SFOY0BdHRUT1LSO0Q": ["R0y03SFOY0BdHRUT1LSO0Q", ["Shanghainese", "Dim Sum", "Noodles"]], "6d4UdQzKaac9h1z8vRkbqg": ["6d4UdQzKaac9h1z8vRkbqg", ["Malaysian"]], "NInbW8FuHAFwz354Ebm4VA": ["NInbW8FuHAFwz354Ebm4VA", ["Salad", "Vegetarian"]], "tM5ooPeeKmjjbtzesvsvtw": ["tM5ooPeeKmjjbtzesvsvtw", ["Vegan", "Latin American"]], "scTDvJ2M2jDbb1ntVeIyxA": ["scTDvJ2M2jDbb1ntVeIyxA", ["Chinese", "Noodles"]], "0zmFmXrFFEWxj8RxpVMfzA": ["0zmFmXrFFEWxj8RxpVMfzA", ["Vietnamese", "Barbeque"]], "YjkEjOJ05z4MVDmbrWvWdQ": ["YjkEjOJ05z4MVDmbrWvWdQ", ["Vietnamese", "Cocktail Bars"]], "5RjZCsXuWPclyrDsnsXw7w": ["5RjZCsXuWPclyrDsnsXw7w", ["Chinese", "Noodles", "Burgers"]], "dIipa0PYSjJmKm6OIcqr5Q": ["dIipa0PYSjJmKm6OIcqr5Q", ["Vegan", "Vegetarian", "Asian Fusion"]], "dtk1Cstz5MHr-B1AOM_nXA": ["dtk1Cstz5MHr-B1AOM_nXA", ["Japanese", "Barbeque", "Asian Fusion"]], "p1n4SeP1goqMJAm390LlBQ": ["p1n4SeP1goqMJAm390LlBQ", ["Thai", "Chinese", "Asian Fusion"]], "IzY4xwbY7YqPoL_-xCSeRA": ["IzY4xwbY7YqPoL_-xCSeRA", ["Poke", "Asian Fusion"]], "q3DA0poiO5h1DPu0Rfhygg": ["q3DA0poiO5h1DPu0Rfhygg", ["Asian Fusion", "Sushi Bars"]], "us2cegdaGlJRLbSLZsu54w": ["us2cegdaGlJRLbSLZsu54w", ["Sushi Bars", "Japanese", "Noodles"]], "HZWHBfeuP4Fb6y8b8uqnbA": ["HZWHBfeuP4Fb6y8b8uqnbA", ["Japanese", "Sushi Bars"]], "09y5uyX7z41mjoA9fVF1bQ": ["09y5uyX7z41mjoA9fVF1bQ", ["Sushi Bars", "Korean", "Chinese"]], "JaKLZrh1Y_2qB_0Gc3bk3A": ["JaKLZrh1Y_2qB_0Gc3bk3A", ["Szechuan", "Cantonese", "Noodles"]], "9GXynHv92V4AaeBb5DExEA": ["9GXynHv92V4AaeBb5DExEA", ["Asian Fusion", "Bars"]], "EYpS39ad-GfC5l2F7PwZig": ["EYpS39ad-GfC5l2F7PwZig", ["Asian Fusion", "Chinese"]], "nd0uXNXaeaDMuMk4C1GusA": ["nd0uXNXaeaDMuMk4C1GusA", ["Indian", "Buffets", "Vegetarian"]], "yEpkPwO6uLfmzp1BMJBUFg": ["yEpkPwO6uLfmzp1BMJBUFg", ["Korean", "Soup", "Seafood"]], "vbL4Ef8zf4dmdR9Gyl5lkw": ["vbL4Ef8zf4dmdR9Gyl5lkw", ["Taiwanese", "Chinese", "Asian Fusion"]], "NwpMub7ITt7sI5rRBvOuQA": ["NwpMub7ITt7sI5rRBvOuQA", ["Bubble Tea", "Waffles", "Asian Fusion"]], "pNeBjEYCmI9gS-GcwRc4Ew": ["pNeBjEYCmI9gS-GcwRc4Ew", ["American (New)", "Vegetarian"]], "AT8y2hH3zcALOhJPzb_hiw": ["AT8y2hH3zcALOhJPzb_hiw", ["Sushi Bars", "Japanese", "Asian Fusion"]], "k3zGo29AJQA8PrDo5mEi7A": ["k3zGo29AJQA8PrDo5mEi7A", ["Korean", "Noodles"]], "gJSX5IDyhjeMjz9IS2DIwQ": ["gJSX5IDyhjeMjz9IS2DIwQ", ["Vegetarian", "Kosher", "Vegan"]], "WHXgDm3kcU-aONfjR8tX0A": ["WHXgDm3kcU-aONfjR8tX0A", ["Japanese", "Sushi Bars", "American (New)"]], "xtxcAUvrD4dWHJd0cwvW1A": ["xtxcAUvrD4dWHJd0cwvW1A", ["Korean", "Noodles"]], "G_C-murI79nWDtR10h14XA": ["G_C-murI79nWDtR10h14XA", ["Asian Fusion", "Sushi Bars", "Japanese"]], "vyRuXNXrKQBP834kGzcm3Q": ["vyRuXNXrKQBP834kGzcm3Q", ["Salad", "Vegetarian"]], "5MDlm5mD7aH0_8FnELr82g": ["5MDlm5mD7aH0_8FnELr82g", ["Salad", "Sandwiches", "Soup"]], "0mRtZ39VQI5CfHEJ7zDwug": ["0mRtZ39VQI5CfHEJ7zDwug", ["Cantonese", "Noodles", "Asian Fusion"]], "8td6qiBvZ-En6gSpPjXWzQ": ["8td6qiBvZ-En6gSpPjXWzQ", ["Shanghainese", "Noodles"]], "KReYd1ipAcFIak--SOJtNg": ["KReYd1ipAcFIak--SOJtNg", ["Desserts", "Thai", "Ice Cream & Frozen Yogurt"]], "Nt3Y26a6OMtdBe8xMMJjqQ": ["Nt3Y26a6OMtdBe8xMMJjqQ", ["Noodles", "Cantonese"]], "HXLDYJ6Fznjn48VbE_8cow": ["HXLDYJ6Fznjn48VbE_8cow", ["Japanese", "Burgers", "Sushi Bars"]], "0XC6L2GCtuaNEI8XFEyD2g": ["0XC6L2GCtuaNEI8XFEyD2g", ["Vegan"]], "-J2yUN8Ako-XLOuZl7UO6Q": ["-J2yUN8Ako-XLOuZl7UO6Q", ["Chinese", "Seafood", "Thai"]], "Tjo8JXQzoBwvw_QYicejiw": ["Tjo8JXQzoBwvw_QYicejiw", ["Japanese", "Taiwanese", "Asian Fusion"]], "qVEmCWCDISUqKRADh0gK9Q": ["qVEmCWCDISUqKRADh0gK9Q", ["Chinese", "Thai"]], "DH6vM_NdIN5q-xfiHnJ3mA": ["DH6vM_NdIN5q-xfiHnJ3mA", ["Chinese", "Asian Fusion"]], "48-joHeN5Y-BWTDI38fzDA": ["48-joHeN5Y-BWTDI38fzDA", ["Chinese", "Asian Fusion"]], "sGkH0pgXE-QrzyNHkSm9Cw": ["sGkH0pgXE-QrzyNHkSm9Cw", ["Delis", "Asian Fusion", "Salad"]], "RD_CkP9ukgTIWMH6dVJGaA": ["RD_CkP9ukgTIWMH6dVJGaA", ["Salad", "Vegan", "Gluten-Free"]], "zb78ua-FlfFRj8v082giBw": ["zb78ua-FlfFRj8v082giBw", ["Chinese", "Noodles"]], "-qH2RpUAZgDtp4Y5d_rI5w": ["-qH2RpUAZgDtp4Y5d_rI5w", ["Vegan", "Fast Food", "Burgers"]], "xemN4tP9RlK5c-yUT-M71Q": ["xemN4tP9RlK5c-yUT-M71Q", ["Mexican", "Bars", "Vegetarian"]], "0CjK3esfpFcxIopebzjFxA": ["0CjK3esfpFcxIopebzjFxA", ["Shanghainese", "Seafood", "Noodles"]], "LvzN8TrUGJRj_UkJV0cAtQ": ["LvzN8TrUGJRj_UkJV0cAtQ", ["Latin American", "Food Delivery Services", "Burgers"]], "g5WYJfH0hWggmdYG2oxsMw": ["g5WYJfH0hWggmdYG2oxsMw", ["Vietnamese", "Noodles", "Sandwiches"]], "fqr2YzqzG7q1ZsuP2klxww": ["fqr2YzqzG7q1ZsuP2klxww", ["Lounges", "Sushi Bars", "Japanese"]], "71EQXj4urSJKrM7bZwM4Fg": ["71EQXj4urSJKrM7bZwM4Fg", ["Chinese", "Thai"]], "HODEF1U9GM0hOcuGgXEhYw": ["HODEF1U9GM0hOcuGgXEhYw", ["Vietnamese"]], "wsMThqit2caUREhOMCOyAQ": ["wsMThqit2caUREhOMCOyAQ", ["Vietnamese"]], "A1ZL9ukJ1m5gxSgHTGs3UQ": ["A1ZL9ukJ1m5gxSgHTGs3UQ", ["Asian Fusion"]], "N8JfRje2vbyEnEOiGgpY7A": ["N8JfRje2vbyEnEOiGgpY7A", ["Sushi Bars", "Asian Fusion", "Chinese"]], "g8i7ZoTri1fUGkaIM6fP9A": ["g8i7ZoTri1fUGkaIM6fP9A", ["Japanese", "Vegan"]], "RTFIMX31BPeZzx7kJJ1SCA": ["RTFIMX31BPeZzx7kJJ1SCA", ["Dim Sum", "Asian Fusion", "Cantonese"]], "TfO9b3q0urwXlSaDXKrirQ": ["TfO9b3q0urwXlSaDXKrirQ", ["Thai"]], "NavBPhyeykbve1uVSOrDPg": ["NavBPhyeykbve1uVSOrDPg", ["American (Traditional)", "Diners", "Soup"]], "tltxRKesOFGcnEklx3vqUA": ["tltxRKesOFGcnEklx3vqUA", ["American (New)", "Asian Fusion"]], "rdo_6F3iH2exAHqSsc6j-A": ["rdo_6F3iH2exAHqSsc6j-A", ["Vietnamese", "Noodles"]], "SP2vm-aBziDECxM3dENNIw": ["SP2vm-aBziDECxM3dENNIw", ["Asian Fusion", "Sushi Bars", "Japanese"]], "EA-Jp5-G61ohe3rj7ofssA": ["EA-Jp5-G61ohe3rj7ofssA", ["Vegan"]], "IYBtdrWFMGq8tjOKgoB5Dw": ["IYBtdrWFMGq8tjOKgoB5Dw", ["Salad", "Vegetarian", "Grocery"]], "6FuUzI7BoL3K6kJfoGwMmA": ["6FuUzI7BoL3K6kJfoGwMmA", ["Food Delivery Services"]], "5DcxBNwS7mSF7vPKS-1cew": ["5DcxBNwS7mSF7vPKS-1cew", ["Salad", "Vegetarian"]], "rnioN9LciPxkfKo799QRCQ": ["rnioN9LciPxkfKo799QRCQ", ["Vietnamese"]], "joSU4pnYVMhAuZ6ccaqqdA": ["joSU4pnYVMhAuZ6ccaqqdA", ["Noodles", "Cantonese", "Hong Kong Style Cafe"]], "LTfR_0NiS7OIRCfkaAJg9w": ["LTfR_0NiS7OIRCfkaAJg9w", ["Japanese", "Sushi Bars", "Soup"]], "FEhAl2T2UGwnsdvjLIQbQA": ["FEhAl2T2UGwnsdvjLIQbQA", ["Salad", "Vegetarian", "Grocery"]], "k4QfaFoqtpEZ1LZylJZqww": ["k4QfaFoqtpEZ1LZylJZqww", ["Sushi Bars", "Japanese", "Asian Fusion"]], "itH4GH2Mw2D5n5kkQAtMog": ["itH4GH2Mw2D5n5kkQAtMog", ["Japanese Curry", "Noodles", "Beer Bar"]], "CHW9sTtJxM6z8cqEy84aWg": ["CHW9sTtJxM6z8cqEy84aWg", ["Vietnamese"]], "tEKxAitFfYl4uYexZtiNNw": ["tEKxAitFfYl4uYexZtiNNw", ["Asian Fusion", "Japanese"]], "6HfkOUronrx92x1dMmwFbA": ["6HfkOUronrx92x1dMmwFbA", ["Vietnamese", "Bubble Tea", "Sandwiches"]], "ECemz7ixbRYZkkDxThcQWg": ["ECemz7ixbRYZkkDxThcQWg", ["Vietnamese", "Sandwiches"]], "sCbkm45j6pKBpq8gxd12LA": ["sCbkm45j6pKBpq8gxd12LA", ["Vietnamese"]], "bRPq-Nmct5bOuOtsu8fC7Q": ["bRPq-Nmct5bOuOtsu8fC7Q", ["American (Traditional)", "Gluten-Free", "Vegetarian"]], "iK0eVDtSFW7cW-4PKhq0WA": ["iK0eVDtSFW7cW-4PKhq0WA", ["Japanese", "Thai"]], "ZxfXy-odIz_Xi1i9Uu00pg": ["ZxfXy-odIz_Xi1i9Uu00pg", ["French", "Bars", "Soup"]], "zYazbSSzg48b7FneTCvwTw": ["zYazbSSzg48b7FneTCvwTw", ["Vegan", "Cafes"]], "JdNT5inXTz9xDmZMZ460hw": ["JdNT5inXTz9xDmZMZ460hw", ["Japanese", "Sushi Bars", "Asian Fusion"]], "t4PA7TuIg2TCxBkVuRw7AA": ["t4PA7TuIg2TCxBkVuRw7AA", ["Vietnamese"]], "lnUqcsrdbY6mK0HtkNFlng": ["lnUqcsrdbY6mK0HtkNFlng", ["Salad", "Vegetarian"]], "wm9vD7JetCskxM7RV2CTbA": ["wm9vD7JetCskxM7RV2CTbA", ["Hawaiian", "Poke", "Asian Fusion"]], "8ObY1IkKWvx99nIOqRBshA": ["8ObY1IkKWvx99nIOqRBshA", ["Noodles"]], "Rwtv0CMqLOmpw0iWzTOF2A": ["Rwtv0CMqLOmpw0iWzTOF2A", ["Korean", "Vietnamese", "Asian Fusion"]], "6wOUVcvw9KBn-ToylxIUmQ": ["6wOUVcvw9KBn-ToylxIUmQ", ["Vietnamese"]], "Z9t-ou4JhiBu-n4-F7hDng": ["Z9t-ou4JhiBu-n4-F7hDng", ["Noodles", "Dim Sum"]], "3VQEgSJShNfBka84IC-baA": ["3VQEgSJShNfBka84IC-baA", ["Pubs", "Soup", "Venues & Event Spaces"]], "ZbPQb_atkkTNxvjlXBk5Cg": ["ZbPQb_atkkTNxvjlXBk5Cg", ["Salad", "Chicken Shop", "Soup"]], "jvPYm9rYK-5ddnjU30Oz4Q": ["jvPYm9rYK-5ddnjU30Oz4Q", ["American (New)", "Vegan", "Vegetarian"]]}